{"skeleton":{"hash":"0XluGFTMN/4BJjQPQqyHfMWsf0E","spine":"3.8.99","x":-394,"y":-278.25,"width":774,"height":774,"images":"./images/","audio":"D:/_Mask/_CompanyProjects"},"bones":[{"name":"root","scaleX":1.29,"scaleY":1.29},{"name":"Center","parent":"root"},{"name":"FX","parent":"Center"},{"name":"FX_Light","parent":"FX","x":-151.97,"y":-24.06},{"name":"FX_Light2","parent":"FX","x":-49.78,"y":101.45},{"name":"FX_Light3","parent":"FX","x":9.55,"y":-58.11},{"name":"FX_Light4","parent":"FX","x":83.73,"y":37.5},{"name":"FX_Light5","parent":"FX","x":125.61,"y":-100.12},{"name":"Bowl_Center","parent":"root"},{"name":"NG_Coin","parent":"root","x":5.15,"y":1.7},{"name":"FG_Coin","parent":"root"},{"name":"FX2","parent":"FX","x":-1.74,"y":-24.8},{"name":"FX_Light6","parent":"FX","x":12.45,"y":53.34},{"name":"FX_Light7","parent":"FX","x":-72.96,"y":31.91},{"name":"FX_Light8","parent":"FX","x":12.45,"y":53.34},{"name":"FX_Light9","parent":"FX","x":-49.78,"y":101.45},{"name":"FX_Light10","parent":"FX","x":83.73,"y":37.5},{"name":"FX_Light11","parent":"FX","x":-151.97,"y":-24.06},{"name":"FG_Coin_new","parent":"root"},{"name":"FG_Coin_new_all","parent":"FG_Coin_new"},{"name":"FG_Coin_new_bip","parent":"FG_Coin_new_all"},{"name":"WIN_Coin_a1_1_bip1","parent":"FG_Coin_new_bip"},{"name":"WIN_Coin_a1_1","parent":"WIN_Coin_a1_1_bip1"},{"name":"WIN_Coin_a1","parent":"WIN_Coin_a1_1"},{"name":"WIN_Coin_b1_1_bip1","parent":"FG_Coin_new_bip"},{"name":"WIN_Coin_b1_1","parent":"WIN_Coin_b1_1_bip1"},{"name":"WIN_Coin_b1","parent":"WIN_Coin_b1_1"},{"name":"WIN_Coin_c1_1_bip1","parent":"FG_Coin_new_bip"},{"name":"WIN_Coin_c1_1","parent":"WIN_Coin_c1_1_bip1"},{"name":"WIN_Coin_c1","parent":"WIN_Coin_c1_1"},{"name":"old","parent":"FG_Coin_new"},{"name":"Bowl_Center2","parent":"old","y":-123.82},{"name":"FG_Coin2","parent":"old"},{"name":"FX3","parent":"Bowl_Center2","y":123.82},{"name":"FX_Light12","parent":"FX3","x":-151.97,"y":-24.06},{"name":"FX_Light13","parent":"FX3","x":-49.78,"y":101.45},{"name":"FX_Light14","parent":"FX3","x":9.55,"y":-58.11},{"name":"FX_Light15","parent":"FX3","x":83.73,"y":37.5},{"name":"FX_Light16","parent":"FX3","x":125.61,"y":-100.12},{"name":"FX_Light17","parent":"FX3","x":12.45,"y":53.34},{"name":"FX_Light18","parent":"FX3","x":-72.96,"y":31.91},{"name":"FX_Light19","parent":"FX3","x":12.45,"y":53.34},{"name":"FX_Light20","parent":"FX3","x":-49.78,"y":101.45},{"name":"FX_Light21","parent":"FX3","x":83.73,"y":37.5},{"name":"FX_Light22","parent":"FX3","x":-151.97,"y":-24.06},{"name":"FG_Glow_a","parent":"Bowl_Center2","y":123.82},{"name":"Bowl_Glow2","parent":"Bowl_Center2","y":76.3},{"name":"Bowl_Ring_bip","parent":"Bowl_Center2","y":123.82},{"name":"Bowl_Ring_L","parent":"Bowl_Ring_bip","x":-164.48,"y":-33.63},{"name":"Bowl_Ring_R","parent":"Bowl_Ring_bip","x":160.82,"y":-34.36},{"name":"FG_Glow_b","parent":"old"},{"name":"WIN_Coin_d1_1_bip1","parent":"FG_Coin_new_bip"},{"name":"WIN_Coin_d1_1","parent":"WIN_Coin_d1_1_bip1"},{"name":"WIN_Coin_d1","parent":"WIN_Coin_d1_1"},{"name":"WIN_Coin_e1_1_bip1","parent":"FG_Coin_new_bip"},{"name":"WIN_Coin_e1_1","parent":"WIN_Coin_e1_1_bip1"},{"name":"WIN_Coin_e1","parent":"WIN_Coin_e1_1"},{"name":"WIN_Coin_a1_1_bip2","parent":"FG_Coin_new_bip"},{"name":"WIN_Coin_a1_2","parent":"WIN_Coin_a1_1_bip2"},{"name":"WIN_Coin_a2","parent":"WIN_Coin_a1_2"},{"name":"WIN_Coin_e1_1_bip2","parent":"FG_Coin_new_bip"},{"name":"WIN_Coin_e1_2","parent":"WIN_Coin_e1_1_bip2"},{"name":"WIN_Coin_e2","parent":"WIN_Coin_e1_2"},{"name":"WIN_Coin_b1_1_bip2","parent":"FG_Coin_new_bip"},{"name":"WIN_Coin_b1_2","parent":"WIN_Coin_b1_1_bip2"},{"name":"WIN_Coin_b2","parent":"WIN_Coin_b1_2"},{"name":"WIN_Coin_c1_1_bip2","parent":"FG_Coin_new_bip"},{"name":"WIN_Coin_c1_2","parent":"WIN_Coin_c1_1_bip2"},{"name":"WIN_Coin_c2","parent":"WIN_Coin_c1_2"},{"name":"WIN_Coin_d1_1_bip2","parent":"FG_Coin_new_bip"},{"name":"WIN_Coin_d1_2","parent":"WIN_Coin_d1_1_bip2"},{"name":"WIN_Coin_d2","parent":"WIN_Coin_d1_2"},{"name":"WIN_Coin_a1_1_bip3","parent":"FG_Coin_new_bip"},{"name":"WIN_Coin_a1_3","parent":"WIN_Coin_a1_1_bip3"},{"name":"WIN_Coin_a3","parent":"WIN_Coin_a1_3"},{"name":"WIN_Coin_e1_1_bip3","parent":"FG_Coin_new_bip"},{"name":"WIN_Coin_e1_3","parent":"WIN_Coin_e1_1_bip3"},{"name":"WIN_Coin_e3","parent":"WIN_Coin_e1_3"},{"name":"WIN_Coin_a1_1_bip4","parent":"FG_Coin_new_bip"},{"name":"WIN_Coin_a1_4","parent":"WIN_Coin_a1_1_bip4"},{"name":"WIN_Coin_a4","parent":"WIN_Coin_a1_4"},{"name":"WIN_Coin_e1_1_bip4","parent":"FG_Coin_new_bip"},{"name":"WIN_Coin_e1_4","parent":"WIN_Coin_e1_1_bip4"},{"name":"WIN_Coin_e4","parent":"WIN_Coin_e1_4"},{"name":"FG_Coin_new_bip2","parent":"FG_Coin_new_all"},{"name":"WIN_Coin_a1_1_bip5","parent":"FG_Coin_new_bip2"},{"name":"WIN_Coin_a1_5","parent":"WIN_Coin_a1_1_bip5"},{"name":"WIN_Coin_a5","parent":"WIN_Coin_a1_5"},{"name":"WIN_Coin_b1_1_bip3","parent":"FG_Coin_new_bip2"},{"name":"WIN_Coin_b1_3","parent":"WIN_Coin_b1_1_bip3"},{"name":"WIN_Coin_b3","parent":"WIN_Coin_b1_3"},{"name":"WIN_Coin_c1_1_bip3","parent":"FG_Coin_new_bip2"},{"name":"WIN_Coin_c1_3","parent":"WIN_Coin_c1_1_bip3"},{"name":"WIN_Coin_c3","parent":"WIN_Coin_c1_3"},{"name":"WIN_Coin_d1_1_bip3","parent":"FG_Coin_new_bip2"},{"name":"WIN_Coin_d1_3","parent":"WIN_Coin_d1_1_bip3"},{"name":"WIN_Coin_d3","parent":"WIN_Coin_d1_3"},{"name":"WIN_Coin_e1_1_bip5","parent":"FG_Coin_new_bip2"},{"name":"WIN_Coin_e1_5","parent":"WIN_Coin_e1_1_bip5"},{"name":"WIN_Coin_e5","parent":"WIN_Coin_e1_5","rotation":30},{"name":"WIN_Coin_a1_1_bip6","parent":"FG_Coin_new_bip2"},{"name":"WIN_Coin_a1_6","parent":"WIN_Coin_a1_1_bip6"},{"name":"WIN_Coin_a6","parent":"WIN_Coin_a1_6"},{"name":"WIN_Coin_e1_1_bip6","parent":"FG_Coin_new_bip2"},{"name":"WIN_Coin_e1_6","parent":"WIN_Coin_e1_1_bip6"},{"name":"WIN_Coin_e6","parent":"WIN_Coin_e1_6"},{"name":"WIN_Coin_b1_1_bip4","parent":"FG_Coin_new_bip2"},{"name":"WIN_Coin_b1_4","parent":"WIN_Coin_b1_1_bip4"},{"name":"WIN_Coin_b4","parent":"WIN_Coin_b1_4"},{"name":"WIN_Coin_c1_1_bip4","parent":"FG_Coin_new_bip2"},{"name":"WIN_Coin_c1_4","parent":"WIN_Coin_c1_1_bip4"},{"name":"WIN_Coin_c4","parent":"WIN_Coin_c1_4"},{"name":"WIN_Coin_d1_1_bip4","parent":"FG_Coin_new_bip2"},{"name":"WIN_Coin_d1_4","parent":"WIN_Coin_d1_1_bip4"},{"name":"WIN_Coin_d4","parent":"WIN_Coin_d1_4"},{"name":"WIN_Coin_a1_1_bip7","parent":"FG_Coin_new_bip2"},{"name":"WIN_Coin_a1_7","parent":"WIN_Coin_a1_1_bip7"},{"name":"WIN_Coin_a7","parent":"WIN_Coin_a1_7"},{"name":"WIN_Coin_e1_1_bip7","parent":"FG_Coin_new_bip2"},{"name":"WIN_Coin_e1_7","parent":"WIN_Coin_e1_1_bip7"},{"name":"WIN_Coin_e7","parent":"WIN_Coin_e1_7"},{"name":"WIN_Coin_a1_1_bip8","parent":"FG_Coin_new_bip2"},{"name":"WIN_Coin_a1_8","parent":"WIN_Coin_a1_1_bip8"},{"name":"WIN_Coin_a8","parent":"WIN_Coin_a1_8"},{"name":"WIN_Coin_e1_1_bip8","parent":"FG_Coin_new_bip2"},{"name":"WIN_Coin_e1_8","parent":"WIN_Coin_e1_1_bip8"},{"name":"WIN_Coin_e8","parent":"WIN_Coin_e1_8"},{"name":"FG_Money_Down_new","parent":"Bowl_Center2","y":157.42},{"name":"FG_Coin_new_bip3","parent":"FG_Coin_new_all"},{"name":"WIN_Coin_a1_1_bip9","parent":"FG_Coin_new_bip3"},{"name":"WIN_Coin_a1_9","parent":"WIN_Coin_a1_1_bip9"},{"name":"WIN_Coin_a9","parent":"WIN_Coin_a1_9"},{"name":"WIN_Coin_e1_1_bip9","parent":"FG_Coin_new_bip3"},{"name":"WIN_Coin_e1_9","parent":"WIN_Coin_e1_1_bip9"},{"name":"WIN_Coin_e9","parent":"WIN_Coin_e1_9"},{"name":"WIN_Coin_a1_1_bip10","parent":"FG_Coin_new_bip3"},{"name":"WIN_Coin_a1_10","parent":"WIN_Coin_a1_1_bip10"},{"name":"WIN_Coin_a10","parent":"WIN_Coin_a1_10"},{"name":"WIN_Coin_e1_1_bip10","parent":"FG_Coin_new_bip3"},{"name":"WIN_Coin_e1_10","parent":"WIN_Coin_e1_1_bip10"},{"name":"WIN_Coin_e10","parent":"WIN_Coin_e1_10"},{"name":"WIN_Coin_a1_1_bip11","parent":"FG_Coin_new_bip3"},{"name":"WIN_Coin_a1_11","parent":"WIN_Coin_a1_1_bip11"},{"name":"WIN_Coin_a11","parent":"WIN_Coin_a1_11"},{"name":"WIN_Coin_e1_1_bip11","parent":"FG_Coin_new_bip3"},{"name":"WIN_Coin_e1_11","parent":"WIN_Coin_e1_1_bip11"},{"name":"WIN_Coin_e11","parent":"WIN_Coin_e1_11"},{"name":"WIN_Coin_a1_1_bip12","parent":"FG_Coin_new_bip3"},{"name":"WIN_Coin_a1_12","parent":"WIN_Coin_a1_1_bip12"},{"name":"WIN_Coin_a12","parent":"WIN_Coin_a1_12"},{"name":"WIN_Coin_e1_1_bip12","parent":"FG_Coin_new_bip3"},{"name":"WIN_Coin_e1_12","parent":"WIN_Coin_e1_1_bip12"},{"name":"WIN_Coin_e12","parent":"WIN_Coin_e1_12"},{"name":"FG_Coin_new_bip4","parent":"FG_Coin_new_all"},{"name":"WIN_Coin_a1_1_bip13","parent":"FG_Coin_new_bip4"},{"name":"WIN_Coin_a1_13","parent":"WIN_Coin_a1_1_bip13"},{"name":"WIN_Coin_a13","parent":"WIN_Coin_a1_13"},{"name":"WIN_Coin_e1_1_bip13","parent":"FG_Coin_new_bip4"},{"name":"WIN_Coin_e1_13","parent":"WIN_Coin_e1_1_bip13"},{"name":"WIN_Coin_e13","parent":"WIN_Coin_e1_13"},{"name":"WIN_Coin_a1_1_bip14","parent":"FG_Coin_new_bip4"},{"name":"WIN_Coin_a1_14","parent":"WIN_Coin_a1_1_bip14"},{"name":"WIN_Coin_a14","parent":"WIN_Coin_a1_14"},{"name":"WIN_Coin_e1_1_bip14","parent":"FG_Coin_new_bip4"},{"name":"WIN_Coin_e1_14","parent":"WIN_Coin_e1_1_bip14"},{"name":"WIN_Coin_e14","parent":"WIN_Coin_e1_14"},{"name":"WIN_Coin_a1_1_bip15","parent":"FG_Coin_new_bip4"},{"name":"WIN_Coin_a1_15","parent":"WIN_Coin_a1_1_bip15"},{"name":"WIN_Coin_a15","parent":"WIN_Coin_a1_15"},{"name":"WIN_Coin_e1_1_bip15","parent":"FG_Coin_new_bip4"},{"name":"WIN_Coin_e1_15","parent":"WIN_Coin_e1_1_bip15"},{"name":"WIN_Coin_e15","parent":"WIN_Coin_e1_15"},{"name":"WIN_Coin_a1_1_bip16","parent":"FG_Coin_new_bip4"},{"name":"WIN_Coin_a1_16","parent":"WIN_Coin_a1_1_bip16"},{"name":"WIN_Coin_a16","parent":"WIN_Coin_a1_16"},{"name":"WIN_Coin_e1_1_bip16","parent":"FG_Coin_new_bip4"},{"name":"WIN_Coin_e1_16","parent":"WIN_Coin_e1_1_bip16"},{"name":"WIN_Coin_e16","parent":"WIN_Coin_e1_16"},{"name":"FG_Money_all_light_bip","parent":"FG_Money_Down_new","y":-10.91},{"name":"FG_Money_Down_light1","parent":"FG_Money_all_light_bip","x":-5.43,"y":-2.15},{"name":"FG_Money_Down_light_up","parent":"FG_Money_all_light_bip","x":-5.43,"y":-2.15},{"name":"FG_Coin3","parent":"FG_Money_Down_new","y":-33.6},{"name":"FG_Money_Down_light3","parent":"FG_Money_all_light_bip","x":-5.43,"y":-2.15}],"slots":[{"name":"Bowl_In","bone":"Bowl_Center","attachment":"Bowl_In"},{"name":"Bowl_In2","bone":"Bowl_Center2","attachment":"Bowl_In"},{"name":"FG_Money_Shadow","bone":"FG_Coin","attachment":"FG_Money_Shadow","blend":"multiply"},{"name":"FG_Money_Shadow2","bone":"Bowl_Center2","attachment":"FG_Money_Shadow","blend":"multiply"},{"name":"Bowl_Outer","bone":"Bowl_Center","attachment":"Bowl_Outer"},{"name":"Bowl_Outer2","bone":"Bowl_Center2","attachment":"Bowl_Outer"},{"name":"Bowl_Outer2_light","bone":"Bowl_Center2","attachment":"Bowl_Outer","blend":"additive"},{"name":"Character/Character_Bowl/Character_Bowl_0005","bone":"FX2","attachment":"Character/Character_Bowl/Character_Bowl_0005","blend":"additive"},{"name":"Character/Character_Bowl/Character_Bowl_0015","bone":"FX2","attachment":"Character/Character_Bowl/Character_Bowl_0015","blend":"additive"},{"name":"Character/Character_Bowl/Character_Bowl_0025","bone":"FX2","attachment":"Character/Character_Bowl/Character_Bowl_0025","blend":"additive"},{"name":"Character/Character_Bowl/Character_Bowl_0035","bone":"FX2","attachment":"Character/Character_Bowl/Character_Bowl_0035","blend":"additive"},{"name":"Character/Character_Bowl/Character_Bowl_0045","bone":"FX2","attachment":"Character/Character_Bowl/Character_Bowl_0045","blend":"additive"},{"name":"Character/Character_Bowl/Character_Bowl_0055","bone":"FX2","attachment":"Character/Character_Bowl/Character_Bowl_0055","blend":"additive"},{"name":"Character/Character_Bowl/Character_Bowl_0065","bone":"FX2","attachment":"Character/Character_Bowl/Character_Bowl_0065","blend":"additive"},{"name":"Character/Character_Bowl/Character_Bowl_0075","bone":"FX2","attachment":"Character/Character_Bowl/Character_Bowl_0075","blend":"additive"},{"name":"Character/Character_Bowl/Character_Bowl_0085","bone":"FX2","attachment":"Character/Character_Bowl/Character_Bowl_0085","blend":"additive"},{"name":"Character/Character_Bowl/Character_Bowl_0095","bone":"FX2","attachment":"Character/Character_Bowl/Character_Bowl_0095","blend":"additive"},{"name":"Character/Character_Bowl/Character_Bowl_0105","bone":"FX2","attachment":"Character/Character_Bowl/Character_Bowl_0105","blend":"additive"},{"name":"Character/Character_Bowl/Character_Bowl_0115","bone":"FX2","attachment":"Character/Character_Bowl/Character_Bowl_0115","blend":"additive"},{"name":"Character/Character_Bowl/Character_Bowl_0118","bone":"FX2","attachment":"Character/Character_Bowl/Character_Bowl_0118","blend":"additive"},{"name":"FG_Money_Up","bone":"FG_Coin","attachment":"FG_Money_Up"},{"name":"FG_Money_Up2","bone":"FG_Coin2","attachment":"FG_Money_Up"},{"name":"NG_Money","bone":"NG_Coin","attachment":"NG_Money"},{"name":"NG_Glow","bone":"NG_Coin","attachment":"NG_Glow"},{"name":"Bowl_Ring_L","bone":"Bowl_Center","attachment":"Bowl_Ring_L"},{"name":"Bowl_Ring_R","bone":"Bowl_Center","attachment":"Bowl_Ring_R"},{"name":"Bowl_Ring_L_light","bone":"Bowl_Center","attachment":"Bowl_Ring_L","blend":"additive"},{"name":"Bowl_Ring_R3_light","bone":"Bowl_Center","attachment":"Bowl_Ring_R","blend":"additive"},{"name":"Bowl_Ring_L2","bone":"Bowl_Ring_L","attachment":"Bowl_Ring_L"},{"name":"Bowl_Ring_L2_light","bone":"Bowl_Ring_L","attachment":"Bowl_Ring_L","blend":"additive"},{"name":"Bowl_Ring_R2","bone":"Bowl_Ring_R","attachment":"Bowl_Ring_R"},{"name":"Bowl_Ring_R2_light","bone":"Bowl_Ring_R","attachment":"Bowl_Ring_R","blend":"additive"},{"name":"Bowl_Glow","bone":"Bowl_Center","attachment":"Bowl_Glow"},{"name":"FG_Diamond_04","bone":"FG_Coin","attachment":"FG_Diamond_04"},{"name":"FG_Money_Down","bone":"FG_Coin","attachment":"FG_Money_Down"},{"name":"FG_Diamond_03","bone":"FG_Coin","attachment":"FG_Diamond_03"},{"name":"FG_Diamond_02","bone":"FG_Coin","attachment":"FG_Diamond_02"},{"name":"FG_Diamond_01","bone":"FG_Coin","attachment":"FG_Diamond_01"},{"name":"FG_Glow","bone":"FG_Coin","attachment":"FG_Glow"},{"name":"Sym_WD/Sym_Words_Star","bone":"FX_Light","attachment":"Sym_WD/Sym_Words_Star","blend":"additive"},{"name":"Sym_WD/Sym_Words_Star11","bone":"FX_Light11","attachment":"Sym_WD/Sym_Words_Star","blend":"additive"},{"name":"Sym_WD/Sym_Words_Star2","bone":"FX_Light2","attachment":"Sym_WD/Sym_Words_Star","blend":"additive"},{"name":"Sym_WD/Sym_Words_Star9","bone":"FX_Light9","attachment":"Sym_WD/Sym_Words_Star","blend":"additive"},{"name":"Sym_WD/Sym_Words_Star7","bone":"FX_Light7","attachment":"Sym_WD/Sym_Words_Star","blend":"additive"},{"name":"Sym_WD/Sym_Words_Star3","bone":"FX_Light3","attachment":"Sym_WD/Sym_Words_Star","blend":"additive"},{"name":"Sym_WD/Sym_Words_Star4","bone":"FX_Light4","attachment":"Sym_WD/Sym_Words_Star","blend":"additive"},{"name":"Sym_WD/Sym_Words_Star10","bone":"FX_Light10","attachment":"Sym_WD/Sym_Words_Star","blend":"additive"},{"name":"Sym_WD/Sym_Words_Star6","bone":"FX_Light6","attachment":"Sym_WD/Sym_Words_Star","blend":"additive"},{"name":"Sym_WD/Sym_Words_Star8","bone":"FX_Light8","attachment":"Sym_WD/Sym_Words_Star","blend":"additive"},{"name":"Sym_WD/Sym_Words_Star5","bone":"FX_Light5","attachment":"Sym_WD/Sym_Words_Star","blend":"additive"},{"name":"FG_Diamond_4","bone":"FG_Coin3","attachment":"FG_Diamond_04"},{"name":"FG_Money_Down2","bone":"FG_Coin3","attachment":"FG_Money_Down"},{"name":"FG_Diamond_3","bone":"FG_Coin3","attachment":"FG_Diamond_03"},{"name":"FG_Diamond_2","bone":"FG_Coin3","attachment":"FG_Diamond_02"},{"name":"FG_Diamond_1","bone":"FG_Coin3","attachment":"FG_Diamond_01"},{"name":"FG_Money_Down_light1","bone":"FG_Money_Down_light1","attachment":"FG_Money_Down_light1","blend":"additive"},{"name":"FG_Money_Down_light3","bone":"FG_Money_Down_light3","attachment":"FG_Money_Down_light_d","blend":"additive"},{"name":"FG_Money_Down_light_up","bone":"FG_Money_Down_light_up","attachment":"FG_Money_Down_light","blend":"multiply"},{"name":"Bowl_Glow2","bone":"Bowl_Glow2","attachment":"Bowl_Glow"},{"name":"WIN_Coin_a1","bone":"WIN_Coin_a1","attachment":"Character/WIN_Coin/WIN_Coin_a"},{"name":"WIN_Coin_a9","bone":"WIN_Coin_a9","attachment":"Character/WIN_Coin/WIN_Coin_a"},{"name":"WIN_Coin_a13","bone":"WIN_Coin_a13","attachment":"Character/WIN_Coin/WIN_Coin_a"},{"name":"WIN_Coin_a5","bone":"WIN_Coin_a5","attachment":"Character/WIN_Coin/WIN_Coin_a"},{"name":"WIN_Coin_a3","bone":"WIN_Coin_a3","attachment":"Character/WIN_Coin/WIN_Coin_f"},{"name":"WIN_Coin_a11","bone":"WIN_Coin_a11","attachment":"Character/WIN_Coin/WIN_Coin_f"},{"name":"WIN_Coin_a15","bone":"WIN_Coin_a15","attachment":"Character/WIN_Coin/WIN_Coin_f"},{"name":"WIN_Coin_a7","bone":"WIN_Coin_a7","attachment":"Character/WIN_Coin/WIN_Coin_f"},{"name":"WIN_Coin_a4","bone":"WIN_Coin_a4","attachment":"Character/WIN_Coin/WIN_Coin_f"},{"name":"WIN_Coin_a12","bone":"WIN_Coin_a12","attachment":"Character/WIN_Coin/WIN_Coin_f"},{"name":"WIN_Coin_a16","bone":"WIN_Coin_a16","attachment":"Character/WIN_Coin/WIN_Coin_f"},{"name":"WIN_Coin_a8","bone":"WIN_Coin_a8","attachment":"Character/WIN_Coin/WIN_Coin_f"},{"name":"WIN_Coin_a2","bone":"WIN_Coin_a2","attachment":"Character/WIN_Coin/WIN_Coin_a"},{"name":"WIN_Coin_a10","bone":"WIN_Coin_a10","attachment":"Character/WIN_Coin/WIN_Coin_a"},{"name":"WIN_Coin_a14","bone":"WIN_Coin_a14","attachment":"Character/WIN_Coin/WIN_Coin_a"},{"name":"WIN_Coin_a6","bone":"WIN_Coin_a6","attachment":"Character/WIN_Coin/WIN_Coin_a"},{"name":"WIN_Coin_b","bone":"WIN_Coin_b1","attachment":"Character/WIN_Coin/WIN_Coin_b"},{"name":"WIN_Coin_b3","bone":"WIN_Coin_b3","attachment":"Character/WIN_Coin/WIN_Coin_b"},{"name":"WIN_Coin_b2","bone":"WIN_Coin_b2","attachment":"Character/WIN_Coin/WIN_Coin_b"},{"name":"WIN_Coin_b4","bone":"WIN_Coin_b4","attachment":"FG_Diamond_04"},{"name":"WIN_Coin_c","bone":"WIN_Coin_c1","attachment":"Character/WIN_Coin/WIN_Coin_c"},{"name":"WIN_Coin_c3","bone":"WIN_Coin_c3","attachment":"Character/WIN_Coin/WIN_Coin_c"},{"name":"WIN_Coin_c2","bone":"WIN_Coin_c2","attachment":"Character/WIN_Coin/WIN_Coin_c"},{"name":"WIN_Coin_c4","bone":"WIN_Coin_c4","attachment":"FG_Diamond_04"},{"name":"FG_Glow_a","bone":"FG_Glow_a","attachment":"FG_Glow_a"},{"name":"FG_Glow_b","bone":"FG_Glow_b","attachment":"FG_Glow_b"},{"name":"Sym_WD/Sym_Words_Star12","bone":"FX_Light12","attachment":"Sym_WD/Sym_Words_Star","blend":"additive"},{"name":"Sym_WD/Sym_Words_Star22","bone":"FX_Light22","attachment":"Sym_WD/Sym_Words_Star","blend":"additive"},{"name":"Sym_WD/Sym_Words_Star13","bone":"FX_Light13","attachment":"Sym_WD/Sym_Words_Star","blend":"additive"},{"name":"Sym_WD/Sym_Words_Star20","bone":"FX_Light20","attachment":"Sym_WD/Sym_Words_Star","blend":"additive"},{"name":"Sym_WD/Sym_Words_Star18","bone":"FX_Light18","attachment":"Sym_WD/Sym_Words_Star","blend":"additive"},{"name":"Sym_WD/Sym_Words_Star14","bone":"FX_Light14","attachment":"Sym_WD/Sym_Words_Star","blend":"additive"},{"name":"Sym_WD/Sym_Words_Star15","bone":"FX_Light15","attachment":"Sym_WD/Sym_Words_Star","blend":"additive"},{"name":"Sym_WD/Sym_Words_Star21","bone":"FX_Light21","attachment":"Sym_WD/Sym_Words_Star","blend":"additive"},{"name":"Sym_WD/Sym_Words_Star17","bone":"FX_Light17","attachment":"Sym_WD/Sym_Words_Star","blend":"additive"},{"name":"Sym_WD/Sym_Words_Star19","bone":"FX_Light19","attachment":"Sym_WD/Sym_Words_Star","blend":"additive"},{"name":"Sym_WD/Sym_Words_Star16","bone":"FX_Light16","attachment":"Sym_WD/Sym_Words_Star","blend":"additive"},{"name":"WIN_Coin_d","bone":"WIN_Coin_d1","attachment":"Character/WIN_Coin/WIN_Coin_d"},{"name":"WIN_Coin_d3","bone":"WIN_Coin_d3","attachment":"Character/WIN_Coin/WIN_Coin_b"},{"name":"WIN_Coin_d2","bone":"WIN_Coin_d2","attachment":"Character/WIN_Coin/WIN_Coin_d"},{"name":"WIN_Coin_d4","bone":"WIN_Coin_d4","attachment":"Character/WIN_Coin/WIN_Coin_d"},{"name":"WIN_Coin_e","bone":"WIN_Coin_e1","attachment":"Character/WIN_Coin/WIN_Coin_e"},{"name":"WIN_Coin_e9","bone":"WIN_Coin_e9","attachment":"Character/WIN_Coin/WIN_Coin_e"},{"name":"WIN_Coin_e13","bone":"WIN_Coin_e13","attachment":"Character/WIN_Coin/WIN_Coin_e"},{"name":"WIN_Coin_e5","bone":"WIN_Coin_e5","attachment":"Character/WIN_Coin/WIN_Coin_e"},{"name":"WIN_Coin_e3","bone":"WIN_Coin_e3","attachment":"Character/WIN_Coin/WIN_Coin_g"},{"name":"WIN_Coin_e11","bone":"WIN_Coin_e11","attachment":"Character/WIN_Coin/WIN_Coin_g"},{"name":"WIN_Coin_e15","bone":"WIN_Coin_e15","attachment":"Character/WIN_Coin/WIN_Coin_g"},{"name":"WIN_Coin_e7","bone":"WIN_Coin_e7","attachment":"Character/WIN_Coin/WIN_Coin_g"},{"name":"WIN_Coin_e4","bone":"WIN_Coin_e4","attachment":"Character/WIN_Coin/WIN_Coin_g"},{"name":"WIN_Coin_e12","bone":"WIN_Coin_e12","attachment":"Character/WIN_Coin/WIN_Coin_g"},{"name":"WIN_Coin_e16","bone":"WIN_Coin_e16","attachment":"Character/WIN_Coin/WIN_Coin_g"},{"name":"WIN_Coin_e8","bone":"WIN_Coin_e8","attachment":"Character/WIN_Coin/WIN_Coin_g"},{"name":"WIN_Coin_e2","bone":"WIN_Coin_e2","attachment":"Character/WIN_Coin/WIN_Coin_e"},{"name":"WIN_Coin_e10","bone":"WIN_Coin_e10","attachment":"Character/WIN_Coin/WIN_Coin_e"},{"name":"WIN_Coin_e14","bone":"WIN_Coin_e14","attachment":"Character/WIN_Coin/WIN_Coin_e"},{"name":"WIN_Coin_e6","bone":"WIN_Coin_e6","attachment":"Character/WIN_Coin/WIN_Coin_e"}],"skins":[{"name":"default","attachments":{"Bowl_Glow":{"Bowl_Glow":{"x":9,"y":-40,"width":392,"height":156}},"Bowl_Glow2":{"Bowl_Glow":{"x":9,"y":7.52,"width":392,"height":156}},"Bowl_In":{"Bowl_In":{"x":-0.5,"y":43,"width":299,"height":72}},"Bowl_In2":{"Bowl_In":{"x":-0.5,"y":166.82,"width":299,"height":72}},"Bowl_Outer":{"Bowl_Outer":{"x":-0.5,"y":-25,"width":357,"height":210}},"Bowl_Outer2":{"Bowl_Outer":{"x":-0.5,"y":98.82,"width":357,"height":210}},"Bowl_Outer2_light":{"Bowl_Outer":{"x":-0.5,"y":98.82,"width":357,"height":210}},"Bowl_Ring_L":{"Bowl_Ring_L":{"x":-162,"y":-57,"width":24,"height":58}},"Bowl_Ring_L2":{"Bowl_Ring_L":{"x":2.48,"y":-23.37,"width":24,"height":58}},"Bowl_Ring_L2_light":{"Bowl_Ring_L":{"x":2.48,"y":-23.37,"width":24,"height":58}},"Bowl_Ring_L_light":{"Bowl_Ring_L":{"x":-162,"y":-57,"width":24,"height":58}},"Bowl_Ring_R":{"Bowl_Ring_R":{"x":161,"y":-57,"width":24,"height":58}},"Bowl_Ring_R2":{"Bowl_Ring_R":{"x":0.18,"y":-22.64,"width":24,"height":58}},"Bowl_Ring_R2_light":{"Bowl_Ring_R":{"x":0.18,"y":-22.64,"width":24,"height":58}},"Bowl_Ring_R3_light":{"Bowl_Ring_R":{"x":161,"y":-57,"width":24,"height":58}},"Character/Character_Bowl/Character_Bowl_0005":{"Character/Character_Bowl/Character_Bowl_0005":{"x":-107.21,"y":-14.36,"width":137,"height":180}},"Character/Character_Bowl/Character_Bowl_0015":{"Character/Character_Bowl/Character_Bowl_0015":{"x":-95.17,"y":-6.36,"width":159,"height":196}},"Character/Character_Bowl/Character_Bowl_0025":{"Character/Character_Bowl/Character_Bowl_0025":{"x":-83.63,"y":-2.29,"width":184,"height":203}},"Character/Character_Bowl/Character_Bowl_0035":{"Character/Character_Bowl/Character_Bowl_0035":{"x":-75.89,"width":199,"height":207}},"Character/Character_Bowl/Character_Bowl_0045":{"Character/Character_Bowl/Character_Bowl_0045":{"x":-45.3,"width":206,"height":208}},"Character/Character_Bowl/Character_Bowl_0055":{"Character/Character_Bowl/Character_Bowl_0055":{"x":-15.68,"y":3.39,"width":204,"height":201}},"Character/Character_Bowl/Character_Bowl_0065":{"Character/Character_Bowl/Character_Bowl_0065":{"x":22.55,"y":3.18,"width":201,"height":201}},"Character/Character_Bowl/Character_Bowl_0075":{"Character/Character_Bowl/Character_Bowl_0075":{"x":38.94,"width":189,"height":208}},"Character/Character_Bowl/Character_Bowl_0085":{"Character/Character_Bowl/Character_Bowl_0085":{"x":67.31,"width":197,"height":208}},"Character/Character_Bowl/Character_Bowl_0095":{"Character/Character_Bowl/Character_Bowl_0095":{"x":81.02,"width":186,"height":206}},"Character/Character_Bowl/Character_Bowl_0105":{"Character/Character_Bowl/Character_Bowl_0105":{"x":85.07,"y":-3.12,"width":179,"height":202}},"Character/Character_Bowl/Character_Bowl_0115":{"Character/Character_Bowl/Character_Bowl_0115":{"x":109.38,"y":-6.23,"width":132,"height":196}},"Character/Character_Bowl/Character_Bowl_0118":{"Character/Character_Bowl/Character_Bowl_0118":{"x":117.5,"y":-24,"width":115,"height":161}},"FG_Diamond_01":{"FG_Diamond_01":{"x":23.5,"y":51,"width":87,"height":64}},"FG_Diamond_1":{"FG_Diamond_01":{"x":23.5,"y":51,"width":87,"height":64}},"FG_Diamond_02":{"FG_Diamond_02":{"x":46,"y":91.5,"width":64,"height":51}},"FG_Diamond_2":{"FG_Diamond_02":{"x":46,"y":91.5,"width":64,"height":51}},"FG_Diamond_03":{"FG_Diamond_03":{"x":-67.5,"y":46,"width":63,"height":62}},"FG_Diamond_3":{"FG_Diamond_03":{"x":-67.5,"y":46,"width":63,"height":62}},"FG_Diamond_04":{"FG_Diamond_04":{"x":-79,"y":123,"width":38,"height":48}},"FG_Diamond_4":{"FG_Diamond_04":{"x":-79,"y":123,"width":38,"height":48}},"FG_Glow":{"FG_Glow":{"x":-4,"y":3,"width":424,"height":316}},"FG_Glow_a":{"FG_Glow_a":{"x":-4,"y":3,"width":424,"height":316}},"FG_Glow_b":{"FG_Glow_b":{"x":-4,"y":3,"width":424,"height":316}},"FG_Money_Down":{"FG_Money_Down":{"x":-7,"y":81.5,"width":330,"height":153}},"FG_Money_Down2":{"FG_Money_Down":{"x":-7,"y":81.5,"width":330,"height":153}},"FG_Money_Down_light1":{"FG_Money_Down_light1":{"y":63.76,"width":600,"height":600}},"FG_Money_Down_light3":{"FG_Money_Down_light_d":{"y":63.76,"width":600,"height":600}},"FG_Money_Down_light_up":{"FG_Money_Down_light":{"y":63.76,"width":600,"height":600}},"FG_Money_Shadow":{"FG_Money_Shadow":{"x":2.5,"y":29.5,"width":315,"height":85}},"FG_Money_Shadow2":{"FG_Money_Shadow":{"x":2.5,"y":153.32,"width":315,"height":85}},"FG_Money_Up":{"FG_Money_Up":{"x":8,"y":-120,"width":412,"height":48}},"FG_Money_Up2":{"FG_Money_Up":{"x":8,"y":-120,"width":412,"height":48}},"NG_Glow":{"NG_Glow":{"x":3.5,"y":9,"width":287,"height":142}},"NG_Money":{"NG_Money":{"x":1.2,"y":70.15,"width":344,"height":145}},"Sym_WD/Sym_Words_Star":{"Sym_WD/Sym_Words_Star":{"x":11.02,"width":51,"height":44}},"Sym_WD/Sym_Words_Star2":{"Sym_WD/Sym_Words_Star":{"x":11.02,"width":51,"height":44}},"Sym_WD/Sym_Words_Star3":{"Sym_WD/Sym_Words_Star":{"x":11.02,"width":51,"height":44}},"Sym_WD/Sym_Words_Star4":{"Sym_WD/Sym_Words_Star":{"x":11.02,"width":51,"height":44}},"Sym_WD/Sym_Words_Star5":{"Sym_WD/Sym_Words_Star":{"x":11.02,"width":51,"height":44}},"Sym_WD/Sym_Words_Star6":{"Sym_WD/Sym_Words_Star":{"x":11.02,"width":51,"height":44}},"Sym_WD/Sym_Words_Star7":{"Sym_WD/Sym_Words_Star":{"x":11.02,"width":51,"height":44}},"Sym_WD/Sym_Words_Star8":{"Sym_WD/Sym_Words_Star":{"x":11.02,"width":51,"height":44}},"Sym_WD/Sym_Words_Star9":{"Sym_WD/Sym_Words_Star":{"x":11.02,"width":51,"height":44}},"Sym_WD/Sym_Words_Star10":{"Sym_WD/Sym_Words_Star":{"x":11.02,"width":51,"height":44}},"Sym_WD/Sym_Words_Star11":{"Sym_WD/Sym_Words_Star":{"x":11.02,"width":51,"height":44}},"Sym_WD/Sym_Words_Star12":{"Sym_WD/Sym_Words_Star":{"x":11.02,"width":51,"height":44}},"Sym_WD/Sym_Words_Star13":{"Sym_WD/Sym_Words_Star":{"x":11.02,"width":51,"height":44}},"Sym_WD/Sym_Words_Star14":{"Sym_WD/Sym_Words_Star":{"x":11.02,"width":51,"height":44}},"Sym_WD/Sym_Words_Star15":{"Sym_WD/Sym_Words_Star":{"x":11.02,"width":51,"height":44}},"Sym_WD/Sym_Words_Star16":{"Sym_WD/Sym_Words_Star":{"x":11.02,"width":51,"height":44}},"Sym_WD/Sym_Words_Star17":{"Sym_WD/Sym_Words_Star":{"x":11.02,"width":51,"height":44}},"Sym_WD/Sym_Words_Star18":{"Sym_WD/Sym_Words_Star":{"x":11.02,"width":51,"height":44}},"Sym_WD/Sym_Words_Star19":{"Sym_WD/Sym_Words_Star":{"x":11.02,"width":51,"height":44}},"Sym_WD/Sym_Words_Star20":{"Sym_WD/Sym_Words_Star":{"x":11.02,"width":51,"height":44}},"Sym_WD/Sym_Words_Star21":{"Sym_WD/Sym_Words_Star":{"x":11.02,"width":51,"height":44}},"Sym_WD/Sym_Words_Star22":{"Sym_WD/Sym_Words_Star":{"x":11.02,"width":51,"height":44}},"WIN_Coin_a1":{"Character/WIN_Coin/WIN_Coin_a":{"x":0.5,"y":0.5,"width":31,"height":43}},"WIN_Coin_a2":{"Character/WIN_Coin/WIN_Coin_a":{"x":0.5,"y":0.5,"width":31,"height":43}},"WIN_Coin_a3":{"Character/WIN_Coin/WIN_Coin_f":{"x":0.5,"y":0.5,"width":44,"height":20}},"WIN_Coin_a4":{"Character/WIN_Coin/WIN_Coin_f":{"x":0.5,"y":0.5,"width":44,"height":20}},"WIN_Coin_a5":{"Character/WIN_Coin/WIN_Coin_a":{"x":0.5,"y":0.5,"width":31,"height":43}},"WIN_Coin_a6":{"Character/WIN_Coin/WIN_Coin_a":{"x":0.5,"y":0.5,"width":31,"height":43}},"WIN_Coin_a7":{"Character/WIN_Coin/WIN_Coin_f":{"x":0.5,"y":0.5,"width":44,"height":20}},"WIN_Coin_a8":{"Character/WIN_Coin/WIN_Coin_f":{"x":0.5,"y":0.5,"width":44,"height":20}},"WIN_Coin_a9":{"Character/WIN_Coin/WIN_Coin_a":{"x":0.5,"y":0.5,"width":31,"height":43}},"WIN_Coin_a10":{"Character/WIN_Coin/WIN_Coin_a":{"x":0.5,"y":0.5,"width":31,"height":43}},"WIN_Coin_a11":{"Character/WIN_Coin/WIN_Coin_f":{"x":0.5,"y":0.5,"width":44,"height":20}},"WIN_Coin_a12":{"Character/WIN_Coin/WIN_Coin_f":{"x":0.5,"y":0.5,"width":44,"height":20}},"WIN_Coin_a13":{"Character/WIN_Coin/WIN_Coin_a":{"x":0.5,"y":0.5,"width":31,"height":43}},"WIN_Coin_a14":{"Character/WIN_Coin/WIN_Coin_a":{"x":0.5,"y":0.5,"width":31,"height":43}},"WIN_Coin_a15":{"Character/WIN_Coin/WIN_Coin_f":{"x":0.5,"y":0.5,"width":44,"height":20}},"WIN_Coin_a16":{"Character/WIN_Coin/WIN_Coin_f":{"x":0.5,"y":0.5,"width":44,"height":20}},"WIN_Coin_b":{"Character/WIN_Coin/WIN_Coin_b":{"width":40,"height":52}},"WIN_Coin_b2":{"Character/WIN_Coin/WIN_Coin_b":{"width":40,"height":52}},"WIN_Coin_b3":{"Character/WIN_Coin/WIN_Coin_b":{"width":40,"height":52}},"WIN_Coin_b4":{"FG_Diamond_04":{"width":38,"height":48}},"WIN_Coin_c":{"Character/WIN_Coin/WIN_Coin_c":{"y":0.5,"width":38,"height":43}},"WIN_Coin_c2":{"Character/WIN_Coin/WIN_Coin_c":{"y":0.5,"width":38,"height":43}},"WIN_Coin_c3":{"Character/WIN_Coin/WIN_Coin_c":{"y":0.5,"width":38,"height":43}},"WIN_Coin_c4":{"FG_Diamond_04":{"y":0.5,"width":38,"height":48}},"WIN_Coin_d":{"Character/WIN_Coin/WIN_Coin_d":{"x":0.5,"width":87,"height":64}},"WIN_Coin_d2":{"Character/WIN_Coin/WIN_Coin_d":{"x":0.5,"width":87,"height":64}},"WIN_Coin_d3":{"Character/WIN_Coin/WIN_Coin_b":{"x":0.5,"width":40,"height":52}},"WIN_Coin_d4":{"Character/WIN_Coin/WIN_Coin_d":{"x":0.5,"width":87,"height":64}},"WIN_Coin_e":{"Character/WIN_Coin/WIN_Coin_e":{"x":0.5,"y":0.5,"width":43,"height":41}},"WIN_Coin_e2":{"Character/WIN_Coin/WIN_Coin_e":{"x":0.5,"y":0.5,"width":43,"height":41}},"WIN_Coin_e3":{"Character/WIN_Coin/WIN_Coin_g":{"x":0.5,"y":0.5,"width":41,"height":29}},"WIN_Coin_e4":{"Character/WIN_Coin/WIN_Coin_g":{"x":0.5,"y":0.5,"width":41,"height":29}},"WIN_Coin_e5":{"Character/WIN_Coin/WIN_Coin_e":{"x":0.5,"y":0.5,"width":43,"height":41}},"WIN_Coin_e6":{"Character/WIN_Coin/WIN_Coin_e":{"x":0.5,"y":0.5,"width":43,"height":41}},"WIN_Coin_e7":{"Character/WIN_Coin/WIN_Coin_g":{"x":0.5,"y":0.5,"width":41,"height":29}},"WIN_Coin_e8":{"Character/WIN_Coin/WIN_Coin_g":{"x":0.5,"y":0.5,"width":41,"height":29}},"WIN_Coin_e9":{"Character/WIN_Coin/WIN_Coin_e":{"x":0.5,"y":0.5,"width":43,"height":41}},"WIN_Coin_e10":{"Character/WIN_Coin/WIN_Coin_e":{"x":0.5,"y":0.5,"width":43,"height":41}},"WIN_Coin_e11":{"Character/WIN_Coin/WIN_Coin_g":{"x":0.5,"y":0.5,"width":41,"height":29}},"WIN_Coin_e12":{"Character/WIN_Coin/WIN_Coin_g":{"x":0.5,"y":0.5,"width":41,"height":29}},"WIN_Coin_e13":{"Character/WIN_Coin/WIN_Coin_e":{"x":0.5,"y":0.5,"width":43,"height":41}},"WIN_Coin_e14":{"Character/WIN_Coin/WIN_Coin_e":{"x":0.5,"y":0.5,"width":43,"height":41}},"WIN_Coin_e15":{"Character/WIN_Coin/WIN_Coin_g":{"x":0.5,"y":0.5,"width":41,"height":29}},"WIN_Coin_e16":{"Character/WIN_Coin/WIN_Coin_g":{"x":0.5,"y":0.5,"width":41,"height":29}}}}],"animations":{"FG_Loop":{"slots":{"Bowl_Glow2":{"attachment":[{"name":null}]},"Bowl_In2":{"attachment":[{"name":null}]},"Bowl_Outer2":{"attachment":[{"name":null}]},"Bowl_Outer2_light":{"attachment":[{"name":null}]},"Bowl_Ring_L2":{"attachment":[{"name":null}]},"Bowl_Ring_L2_light":{"attachment":[{"name":null}]},"Bowl_Ring_L_light":{"color":[{"color":"ffffff00"},{"time":0.1667,"color":"ffffff82"},{"time":0.6667,"color":"ffffff00"}]},"Bowl_Ring_R2":{"attachment":[{"name":null}]},"Bowl_Ring_R2_light":{"attachment":[{"name":null}]},"Bowl_Ring_R3_light":{"color":[{"color":"ffffff00"},{"time":1.4,"color":"ffffff00"},{"time":1.6333,"color":"ffffff83"},{"time":2,"color":"ffffff00"}]},"Character/Character_Bowl/Character_Bowl_0005":{"color":[{"color":"ffffff00"},{"time":0.1667,"color":"ffffffff"},{"time":0.3333,"color":"ffffff00"}]},"Character/Character_Bowl/Character_Bowl_0015":{"color":[{"color":"ffffff00","curve":"stepped"},{"time":0.1,"color":"ffffff00"},{"time":0.3,"color":"ffffffff"},{"time":0.5,"color":"ffffff00"}]},"Character/Character_Bowl/Character_Bowl_0025":{"color":[{"color":"ffffff00","curve":"stepped"},{"time":0.2,"color":"ffffff00"},{"time":0.4333,"color":"ffffffff"},{"time":0.6667,"color":"ffffff00"}]},"Character/Character_Bowl/Character_Bowl_0035":{"color":[{"color":"ffffff00","curve":"stepped"},{"time":0.4,"color":"ffffff00"},{"time":0.6,"color":"ffffffff"},{"time":0.8667,"color":"ffffff00"}]},"Character/Character_Bowl/Character_Bowl_0045":{"color":[{"color":"ffffff00","curve":"stepped"},{"time":0.5667,"color":"ffffff00"},{"time":0.7667,"color":"ffffffff"},{"time":1,"color":"ffffff00"}]},"Character/Character_Bowl/Character_Bowl_0055":{"color":[{"color":"ffffff00","curve":"stepped"},{"time":0.7,"color":"ffffff00"},{"time":0.9333,"color":"ffffffff"},{"time":1.1667,"color":"ffffff00"}]},"Character/Character_Bowl/Character_Bowl_0065":{"color":[{"color":"ffffff00","curve":"stepped"},{"time":0.8333,"color":"ffffff00"},{"time":1.1,"color":"ffffffff"},{"time":1.3667,"color":"ffffff00"}]},"Character/Character_Bowl/Character_Bowl_0075":{"color":[{"color":"ffffff00","curve":"stepped"},{"time":0.9667,"color":"ffffff00"},{"time":1.2667,"color":"ffffffff"},{"time":1.5667,"color":"ffffff00"}]},"Character/Character_Bowl/Character_Bowl_0085":{"color":[{"color":"ffffff00","curve":"stepped"},{"time":1.1333,"color":"ffffff00"},{"time":1.4333,"color":"ffffffff"},{"time":1.7,"color":"ffffff00"}]},"Character/Character_Bowl/Character_Bowl_0095":{"color":[{"color":"ffffff00","curve":"stepped"},{"time":1.3333,"color":"ffffff00"},{"time":1.6,"color":"ffffffff"},{"time":1.8333,"color":"ffffff00"}]},"Character/Character_Bowl/Character_Bowl_0105":{"color":[{"color":"ffffff00","curve":"stepped"},{"time":1.4667,"color":"ffffff00"},{"time":1.7667,"color":"ffffffff"},{"time":2,"color":"ffffff00"}]},"Character/Character_Bowl/Character_Bowl_0115":{"color":[{"color":"ffffff00","curve":"stepped"},{"time":1.6333,"color":"ffffff00"},{"time":1.8667,"color":"ffffffff"},{"time":2,"color":"ffffff00"}]},"Character/Character_Bowl/Character_Bowl_0118":{"color":[{"color":"ffffff00","curve":"stepped"},{"time":1.6667,"color":"ffffff00"},{"time":1.9333,"color":"ffffffff"},{"time":2,"color":"ffffff00"}]},"FG_Diamond_1":{"attachment":[{"name":null}]},"FG_Diamond_2":{"attachment":[{"name":null}]},"FG_Diamond_3":{"attachment":[{"name":null}]},"FG_Diamond_4":{"attachment":[{"name":null}]},"FG_Glow_a":{"attachment":[{"name":null}]},"FG_Glow_b":{"attachment":[{"name":null}]},"FG_Money_Down2":{"attachment":[{"name":null}]},"FG_Money_Down_light1":{"attachment":[{"name":null}]},"FG_Money_Down_light3":{"attachment":[{"name":null}]},"FG_Money_Down_light_up":{"attachment":[{"name":null}]},"FG_Money_Shadow2":{"attachment":[{"name":null}]},"FG_Money_Up2":{"attachment":[{"name":null}]},"NG_Glow":{"color":[{"color":"ffffff00"}],"attachment":[{"name":null}]},"NG_Money":{"color":[{"color":"ffffff00"}],"attachment":[{"name":null}]},"Sym_WD/Sym_Words_Star12":{"attachment":[{"name":null}]},"Sym_WD/Sym_Words_Star13":{"attachment":[{"name":null}]},"Sym_WD/Sym_Words_Star14":{"attachment":[{"name":null}]},"Sym_WD/Sym_Words_Star15":{"attachment":[{"name":null}]},"Sym_WD/Sym_Words_Star16":{"attachment":[{"name":null}]},"Sym_WD/Sym_Words_Star17":{"attachment":[{"name":null}]},"Sym_WD/Sym_Words_Star18":{"attachment":[{"name":null}]},"Sym_WD/Sym_Words_Star19":{"attachment":[{"name":null}]},"Sym_WD/Sym_Words_Star20":{"attachment":[{"name":null}]},"Sym_WD/Sym_Words_Star21":{"attachment":[{"name":null}]},"Sym_WD/Sym_Words_Star22":{"attachment":[{"name":null}]},"WIN_Coin_a1":{"attachment":[{"name":null}]},"WIN_Coin_a2":{"attachment":[{"name":null}]},"WIN_Coin_a3":{"attachment":[{"name":null}]},"WIN_Coin_a4":{"attachment":[{"name":null}]},"WIN_Coin_a5":{"attachment":[{"name":null}]},"WIN_Coin_a6":{"attachment":[{"name":null}]},"WIN_Coin_a7":{"attachment":[{"name":null}]},"WIN_Coin_a8":{"attachment":[{"name":null}]},"WIN_Coin_a9":{"attachment":[{"name":null}]},"WIN_Coin_a10":{"attachment":[{"name":null}]},"WIN_Coin_a11":{"attachment":[{"name":null}]},"WIN_Coin_a12":{"attachment":[{"name":null}]},"WIN_Coin_a13":{"attachment":[{"name":null}]},"WIN_Coin_a14":{"attachment":[{"name":null}]},"WIN_Coin_a15":{"attachment":[{"name":null}]},"WIN_Coin_a16":{"attachment":[{"name":null}]},"WIN_Coin_b":{"attachment":[{"name":null}]},"WIN_Coin_b2":{"attachment":[{"name":null}]},"WIN_Coin_b3":{"attachment":[{"name":null}]},"WIN_Coin_b4":{"attachment":[{"name":null}]},"WIN_Coin_c":{"attachment":[{"name":null}]},"WIN_Coin_c2":{"attachment":[{"name":null}]},"WIN_Coin_c3":{"attachment":[{"name":null}]},"WIN_Coin_c4":{"attachment":[{"name":null}]},"WIN_Coin_d":{"attachment":[{"name":null}]},"WIN_Coin_d2":{"attachment":[{"name":null}]},"WIN_Coin_d3":{"attachment":[{"name":null}]},"WIN_Coin_d4":{"attachment":[{"name":null}]},"WIN_Coin_e":{"attachment":[{"name":null}]},"WIN_Coin_e2":{"attachment":[{"name":null}]},"WIN_Coin_e3":{"attachment":[{"name":null}]},"WIN_Coin_e4":{"attachment":[{"name":null}]},"WIN_Coin_e5":{"attachment":[{"name":null}]},"WIN_Coin_e6":{"attachment":[{"name":null}]},"WIN_Coin_e7":{"attachment":[{"name":null}]},"WIN_Coin_e8":{"attachment":[{"name":null}]},"WIN_Coin_e9":{"attachment":[{"name":null}]},"WIN_Coin_e10":{"attachment":[{"name":null}]},"WIN_Coin_e11":{"attachment":[{"name":null}]},"WIN_Coin_e12":{"attachment":[{"name":null}]},"WIN_Coin_e13":{"attachment":[{"name":null}]},"WIN_Coin_e14":{"attachment":[{"name":null}]},"WIN_Coin_e15":{"attachment":[{"name":null}]},"WIN_Coin_e16":{"attachment":[{"name":null}]}},"bones":{"FX_Light3":{"rotate":[{"time":0.6},{"time":1.5333,"angle":142.31}],"scale":[{"x":0,"y":0,"curve":"stepped"},{"time":0.6,"x":0,"y":0},{"time":0.8,"x":0.6,"y":0.991},{"time":1.0333,"x":0.6,"y":0.6},{"time":1.5333,"x":0,"y":0}]},"FX_Light5":{"rotate":[{"time":1.2},{"time":2,"angle":121.98}],"scale":[{"x":0,"y":0,"curve":"stepped"},{"time":1.2,"x":0,"y":0},{"time":1.4,"x":0.5,"y":0.5,"curve":"stepped"},{"time":1.6333,"x":0.5,"y":0.5},{"time":2,"x":0,"y":0}]},"FX_Light4":{"rotate":[{"time":0.4},{"time":1.8667,"angle":142.31}],"translate":[{"x":60.95,"y":11.88}],"scale":[{"x":0,"y":0,"curve":"stepped"},{"time":1.3667,"x":0,"y":0},{"time":1.6333,"x":0.3,"y":0.3,"curve":"stepped"},{"time":1.8333,"x":0.3,"y":0.3},{"time":2,"x":0,"y":0}]},"FX_Light2":{"rotate":[{"time":0.6},{"time":1.5333,"angle":142.31}],"translate":[{"x":-100.38,"y":-16.8}],"scale":[{"x":0,"y":0,"curve":"stepped"},{"time":0.1,"x":0,"y":0},{"time":0.3333,"x":0.46,"y":0.46,"curve":"stepped"},{"time":0.6333,"x":0.46,"y":0.46},{"time":1.2333,"x":0,"y":0}]},"FX_Light":{"rotate":[{"time":0.0667},{"time":1,"angle":142.31}],"translate":[{"x":22.61,"y":-101.75}],"scale":[{"x":0,"y":0,"curve":"stepped"},{"time":0.2,"x":0,"y":0},{"time":0.4,"x":0.4,"y":0.4,"curve":"stepped"},{"time":0.6333,"x":0.4,"y":0.4},{"time":1.1333,"x":0,"y":0}]},"FX_Light6":{"rotate":[{"time":0.5667},{"time":1.5667,"angle":142.31}],"translate":[{"x":29.89,"y":62.22}],"scale":[{"x":0,"y":0,"curve":"stepped"},{"time":0.5667,"x":0,"y":0},{"time":0.7667,"x":0.6,"y":0.6,"curve":"stepped"},{"time":1,"x":0.6,"y":0.6},{"time":1.5667,"x":0,"y":0}]},"FX_Light7":{"rotate":[{"time":0.3},{"time":1.2333,"angle":142.31}],"scale":[{"x":0,"y":0,"curve":"stepped"},{"time":0.3,"x":0,"y":0},{"time":0.5,"x":0.46,"y":0.46,"curve":"stepped"},{"time":0.7333,"x":0.46,"y":0.46},{"time":1.2333,"x":0,"y":0}]},"FX_Light8":{"rotate":[{"time":0.8667},{"time":1.8667,"angle":142.31}],"scale":[{"x":0,"y":0,"curve":"stepped"},{"time":0.8667,"x":0,"y":0},{"time":1.0667,"x":0.6,"y":0.6,"curve":"stepped"},{"time":1.3,"x":0.6,"y":0.6},{"time":1.8667,"x":0,"y":0}]},"FX_Light9":{"rotate":[{"time":0.6},{"time":1.5333,"angle":142.31}],"translate":[{"x":-38.46,"y":9.62}],"scale":[{"x":0,"y":0,"curve":"stepped"},{"time":0.6,"x":0,"y":0},{"time":0.8,"x":0.46,"y":0.46,"curve":"stepped"},{"time":1.0333,"x":0.46,"y":0.46},{"time":1.5333,"x":0,"y":0}]},"FX_Light10":{"rotate":[{"time":0.4},{"time":1.8667,"angle":142.31}],"translate":[{"x":23.44,"y":32.45}],"scale":[{"x":0,"y":0,"curve":"stepped"},{"time":0.9667,"x":0,"y":0},{"time":1.1667,"x":0.3,"y":0.3,"curve":"stepped"},{"time":1.4,"x":0.3,"y":0.3},{"time":1.7,"x":0,"y":0}]},"FX_Light11":{"rotate":[{"time":0.0667},{"time":1,"angle":142.31}],"translate":[{"x":-21.35,"y":-12.45}],"scale":[{"x":0,"y":0,"curve":"stepped"},{"time":0.0667,"x":0,"y":0},{"time":0.2667,"x":0.4,"y":0.4,"curve":"stepped"},{"time":0.5,"x":0.4,"y":0.4},{"time":1,"x":0,"y":0}]},"FX_Light12":{"rotate":[{"time":0.0667},{"time":1,"angle":142.31}],"translate":[{"x":22.61,"y":-101.75}],"scale":[{"x":0,"y":0,"curve":"stepped"},{"time":0.2,"x":0,"y":0},{"time":0.4,"x":0.4,"y":0.4,"curve":"stepped"},{"time":0.6333,"x":0.4,"y":0.4},{"time":1.1333,"x":0,"y":0}]},"FX_Light13":{"rotate":[{"time":0.6},{"time":1.5333,"angle":142.31}],"translate":[{"x":-100.38,"y":-16.8}],"scale":[{"x":0,"y":0,"curve":"stepped"},{"time":0.1,"x":0,"y":0},{"time":0.3333,"x":0.46,"y":0.46,"curve":"stepped"},{"time":0.6333,"x":0.46,"y":0.46},{"time":1.2333,"x":0,"y":0}]},"FX_Light14":{"rotate":[{"time":0.6},{"time":1.5333,"angle":142.31}],"scale":[{"x":0,"y":0,"curve":"stepped"},{"time":0.6,"x":0,"y":0},{"time":0.8,"x":0.6,"y":0.991},{"time":1.0333,"x":0.6,"y":0.6},{"time":1.5333,"x":0,"y":0}]},"FX_Light15":{"rotate":[{"time":0.4},{"time":1.8667,"angle":142.31}],"translate":[{"x":60.95,"y":11.88}],"scale":[{"x":0,"y":0,"curve":"stepped"},{"time":1.3667,"x":0,"y":0},{"time":1.6333,"x":0.3,"y":0.3,"curve":"stepped"},{"time":1.8333,"x":0.3,"y":0.3},{"time":2,"x":0,"y":0}]},"FX_Light16":{"rotate":[{"time":1.2},{"time":2,"angle":121.98}],"scale":[{"x":0,"y":0,"curve":"stepped"},{"time":1.2,"x":0,"y":0},{"time":1.4,"x":0.5,"y":0.5,"curve":"stepped"},{"time":1.6333,"x":0.5,"y":0.5},{"time":2,"x":0,"y":0}]},"FX_Light17":{"rotate":[{"time":0.5667},{"time":1.5667,"angle":142.31}],"translate":[{"x":29.89,"y":62.22}],"scale":[{"x":0,"y":0,"curve":"stepped"},{"time":0.5667,"x":0,"y":0},{"time":0.7667,"x":0.6,"y":0.6,"curve":"stepped"},{"time":1,"x":0.6,"y":0.6},{"time":1.5667,"x":0,"y":0}]},"FX_Light18":{"rotate":[{"time":0.3},{"time":1.2333,"angle":142.31}],"scale":[{"x":0,"y":0,"curve":"stepped"},{"time":0.3,"x":0,"y":0},{"time":0.5,"x":0.46,"y":0.46,"curve":"stepped"},{"time":0.7333,"x":0.46,"y":0.46},{"time":1.2333,"x":0,"y":0}]},"FX_Light19":{"rotate":[{"time":0.8667},{"time":1.8667,"angle":142.31}],"scale":[{"x":0,"y":0,"curve":"stepped"},{"time":0.8667,"x":0,"y":0},{"time":1.0667,"x":0.6,"y":0.6,"curve":"stepped"},{"time":1.3,"x":0.6,"y":0.6},{"time":1.8667,"x":0,"y":0}]},"FX_Light20":{"rotate":[{"time":0.6},{"time":1.5333,"angle":142.31}],"translate":[{"x":-38.46,"y":9.62}],"scale":[{"x":0,"y":0,"curve":"stepped"},{"time":0.6,"x":0,"y":0},{"time":0.8,"x":0.46,"y":0.46,"curve":"stepped"},{"time":1.0333,"x":0.46,"y":0.46},{"time":1.5333,"x":0,"y":0}]},"FX_Light21":{"rotate":[{"time":0.4},{"time":1.8667,"angle":142.31}],"translate":[{"x":23.44,"y":32.45}],"scale":[{"x":0,"y":0,"curve":"stepped"},{"time":0.9667,"x":0,"y":0},{"time":1.1667,"x":0.3,"y":0.3,"curve":"stepped"},{"time":1.4,"x":0.3,"y":0.3},{"time":1.7,"x":0,"y":0}]},"FX_Light22":{"rotate":[{"time":0.0667},{"time":1,"angle":142.31}],"translate":[{"x":-21.35,"y":-12.45}],"scale":[{"x":0,"y":0,"curve":"stepped"},{"time":0.0667,"x":0,"y":0},{"time":0.2667,"x":0.4,"y":0.4,"curve":"stepped"},{"time":0.5,"x":0.4,"y":0.4},{"time":1,"x":0,"y":0}]}}},"FG_Win":{"slots":{"Bowl_Glow":{"attachment":[{"name":null}]},"Bowl_Glow2":{"color":[{"color":"ffffffff"},{"time":0.1667,"color":"ffffffc7"},{"time":0.5,"color":"ffffffff"}]},"Bowl_In":{"attachment":[{"name":null}]},"Bowl_Outer":{"attachment":[{"name":null}]},"Bowl_Outer2_light":{"color":[{"color":"ffffff00"},{"time":0.2667,"color":"ffffff64"},{"time":0.5333,"color":"ffffff1e"},{"time":0.6,"color":"ffffff00"}]},"Bowl_Ring_L":{"attachment":[{"name":null}]},"Bowl_Ring_L2_light":{"color":[{"color":"ffffff00"},{"time":0.2667,"color":"ffffff64"},{"time":0.5333,"color":"ffffff1e"},{"time":0.6,"color":"ffffff00"}]},"Bowl_Ring_L_light":{"attachment":[{"name":null}]},"Bowl_Ring_R":{"attachment":[{"name":null}]},"Bowl_Ring_R2_light":{"color":[{"color":"ffffff00"},{"time":0.2667,"color":"ffffff64"},{"time":0.5333,"color":"ffffff1e"},{"time":0.6,"color":"ffffff00"}]},"Bowl_Ring_R3_light":{"attachment":[{"name":null}]},"Character/Character_Bowl/Character_Bowl_0005":{"color":[{"color":"ffffff00"}],"attachment":[{"name":null}]},"Character/Character_Bowl/Character_Bowl_0015":{"color":[{"color":"ffffff00"}],"attachment":[{"name":null}]},"Character/Character_Bowl/Character_Bowl_0025":{"color":[{"color":"ffffff00"}],"attachment":[{"name":null}]},"Character/Character_Bowl/Character_Bowl_0035":{"color":[{"color":"ffffff00"}],"attachment":[{"name":null}]},"Character/Character_Bowl/Character_Bowl_0045":{"color":[{"color":"ffffff00"}],"attachment":[{"name":null}]},"Character/Character_Bowl/Character_Bowl_0055":{"color":[{"color":"ffffff00"}],"attachment":[{"name":null}]},"Character/Character_Bowl/Character_Bowl_0065":{"color":[{"color":"ffffff00"}],"attachment":[{"name":null}]},"Character/Character_Bowl/Character_Bowl_0075":{"color":[{"color":"ffffff00"}],"attachment":[{"name":null}]},"Character/Character_Bowl/Character_Bowl_0085":{"color":[{"color":"ffffff00"}],"attachment":[{"name":null}]},"Character/Character_Bowl/Character_Bowl_0095":{"color":[{"color":"ffffff00"}],"attachment":[{"name":null}]},"Character/Character_Bowl/Character_Bowl_0105":{"color":[{"color":"ffffff00"}],"attachment":[{"name":null}]},"Character/Character_Bowl/Character_Bowl_0115":{"color":[{"color":"ffffff00"}],"attachment":[{"name":null}]},"Character/Character_Bowl/Character_Bowl_0118":{"color":[{"color":"ffffff00"}],"attachment":[{"name":null}]},"FG_Diamond_01":{"attachment":[{"name":null}]},"FG_Diamond_02":{"attachment":[{"name":null}]},"FG_Diamond_03":{"attachment":[{"name":null}]},"FG_Diamond_04":{"attachment":[{"name":null}]},"FG_Glow":{"attachment":[{"name":null}]},"FG_Glow_a":{"color":[{"color":"ffffffff"},{"time":0.1667,"color":"ffffff6a"},{"time":0.4667,"color":"ffffffff"}]},"FG_Money_Down":{"attachment":[{"name":null}]},"FG_Money_Down_light1":{"color":[{"color":"ffffff00"},{"time":0.2333,"color":"ffffff64"},{"time":0.4,"color":"ffffff6e"},{"time":0.5,"color":"ffffff49"},{"time":0.6,"color":"ffffff00"}]},"FG_Money_Down_light3":{"color":[{"color":"ffffff00","curve":"stepped"},{"time":0.2333,"color":"ffffff00"},{"time":0.4,"color":"ffffff9f"},{"time":0.5,"color":"ffffff6a"},{"time":0.6,"color":"ffffff00"}]},"FG_Money_Down_light_up":{"color":[{"color":"ffffff00"},{"time":0.2333,"color":"ffffff45"},{"time":0.4,"color":"ffffff28"},{"time":0.5,"color":"ffffff1a"},{"time":0.6,"color":"ffffff00"}]},"FG_Money_Shadow":{"attachment":[{"name":null}]},"FG_Money_Up":{"attachment":[{"name":null}]},"NG_Glow":{"color":[{"color":"ffffff00"}],"attachment":[{"name":null}]},"NG_Money":{"color":[{"color":"ffffff00"}],"attachment":[{"name":null}]},"Sym_WD/Sym_Words_Star":{"attachment":[{"name":null}]},"Sym_WD/Sym_Words_Star2":{"attachment":[{"name":null}]},"Sym_WD/Sym_Words_Star3":{"attachment":[{"name":null}]},"Sym_WD/Sym_Words_Star4":{"attachment":[{"name":null}]},"Sym_WD/Sym_Words_Star5":{"attachment":[{"name":null}]},"Sym_WD/Sym_Words_Star6":{"attachment":[{"name":null}]},"Sym_WD/Sym_Words_Star7":{"attachment":[{"name":null}]},"Sym_WD/Sym_Words_Star8":{"attachment":[{"name":null}]},"Sym_WD/Sym_Words_Star9":{"attachment":[{"name":null}]},"Sym_WD/Sym_Words_Star10":{"attachment":[{"name":null}]},"Sym_WD/Sym_Words_Star11":{"attachment":[{"name":null}]},"WIN_Coin_a1":{"color":[{"color":"ffffff00","curve":"stepped"},{"time":0.3333,"color":"ffffff00"},{"time":0.4333,"color":"ffffffc7"},{"time":0.5667,"color":"ffffffff","curve":"stepped"},{"time":0.6667,"color":"ffffffff"},{"time":0.7667,"color":"ffffff00"}]},"WIN_Coin_a2":{"color":[{"color":"ffffff00","curve":"stepped"},{"time":0.3667,"color":"ffffff00"},{"time":0.4667,"color":"ffffffc7"},{"time":0.6,"color":"ffffffff","curve":"stepped"},{"time":0.7,"color":"ffffffff"},{"time":0.8,"color":"ffffff00"}]},"WIN_Coin_a3":{"color":[{"color":"ffffff00","curve":"stepped"},{"time":0.3333,"color":"ffffff00"},{"time":0.4333,"color":"ffffffc7"},{"time":0.5667,"color":"ffffffff","curve":"stepped"},{"time":0.6667,"color":"ffffffff"},{"time":0.7667,"color":"ffffff00"}]},"WIN_Coin_a4":{"color":[{"color":"ffffff00","curve":"stepped"},{"time":0.3333,"color":"ffffff00"},{"time":0.4333,"color":"ffffffc7"},{"time":0.5667,"color":"ffffffff","curve":"stepped"},{"time":0.6667,"color":"ffffffff"},{"time":0.7667,"color":"ffffff00"}]},"WIN_Coin_a5":{"color":[{"color":"ffffff00","curve":"stepped"},{"time":0.3667,"color":"ffffff00"},{"time":0.4667,"color":"ffffffc7"},{"time":0.6,"color":"ffffffff","curve":"stepped"},{"time":0.6667,"color":"ffffffff"},{"time":0.8,"color":"ffffff00"}]},"WIN_Coin_a6":{"color":[{"color":"ffffff00","curve":"stepped"},{"time":0.3667,"color":"ffffff00"},{"time":0.4667,"color":"ffffffc7"},{"time":0.6,"color":"ffffffff","curve":"stepped"},{"time":0.6667,"color":"ffffffff"},{"time":0.8,"color":"ffffff00"}]},"WIN_Coin_a7":{"color":[{"color":"ffffff00","curve":"stepped"},{"time":0.3667,"color":"ffffff00"},{"time":0.4667,"color":"ffffffc7"},{"time":0.6,"color":"ffffffff","curve":"stepped"},{"time":0.6667,"color":"ffffffff"},{"time":0.8,"color":"ffffff00"}]},"WIN_Coin_a8":{"color":[{"color":"ffffff00","curve":"stepped"},{"time":0.4,"color":"ffffff00"},{"time":0.5,"color":"ffffffc7"},{"time":0.6333,"color":"ffffffff","curve":"stepped"},{"time":0.7,"color":"ffffffff"},{"time":1,"color":"ffffff00"}]},"WIN_Coin_a9":{"color":[{"color":"ffffff00","curve":"stepped"},{"time":0.2667,"color":"ffffff00"},{"time":0.3667,"color":"ffffffc7"},{"time":0.5,"color":"ffffffff","curve":"stepped"},{"time":0.6,"color":"ffffffff"},{"time":0.7,"color":"ffffff00"}]},"WIN_Coin_a10":{"color":[{"color":"ffffff00","curve":"stepped"},{"time":0.2667,"color":"ffffff00"},{"time":0.3667,"color":"ffffffc7"},{"time":0.5,"color":"ffffffff","curve":"stepped"},{"time":0.6,"color":"ffffffff"},{"time":0.7,"color":"ffffff00"}]},"WIN_Coin_a11":{"color":[{"color":"ffffff00","curve":"stepped"},{"time":0.3333,"color":"ffffff00"},{"time":0.4333,"color":"ffffffc7"},{"time":0.5667,"color":"ffffffff","curve":"stepped"},{"time":0.6667,"color":"ffffffff"},{"time":0.7667,"color":"ffffff00"}]},"WIN_Coin_a12":{"color":[{"color":"ffffff00","curve":"stepped"},{"time":0.2667,"color":"ffffff00"},{"time":0.3667,"color":"ffffffc7"},{"time":0.5,"color":"ffffffff","curve":"stepped"},{"time":0.6,"color":"ffffffff"},{"time":0.7,"color":"ffffff00"}]},"WIN_Coin_a13":{"color":[{"color":"ffffff00","curve":"stepped"},{"time":0.3667,"color":"ffffff00"},{"time":0.4667,"color":"ffffffc7"},{"time":0.5667,"color":"ffffffff","curve":"stepped"},{"time":0.6667,"color":"ffffffff"},{"time":0.7667,"color":"ffffff00"}]},"WIN_Coin_a14":{"color":[{"color":"ffffff00","curve":"stepped"},{"time":0.3667,"color":"ffffff00"},{"time":0.4667,"color":"ffffffc7"},{"time":0.5667,"color":"ffffffff","curve":"stepped"},{"time":0.6667,"color":"ffffffff"},{"time":0.7667,"color":"ffffff00"}]},"WIN_Coin_a15":{"color":[{"color":"ffffff00","curve":"stepped"},{"time":0.4333,"color":"ffffff00"},{"time":0.5333,"color":"ffffffc7"},{"time":0.6333,"color":"ffffffff","curve":"stepped"},{"time":0.7333,"color":"ffffffff"},{"time":0.8333,"color":"ffffff00"}]},"WIN_Coin_a16":{"color":[{"color":"ffffff00","curve":"stepped"},{"time":0.3667,"color":"ffffff00"},{"time":0.4667,"color":"ffffffc7"},{"time":0.5667,"color":"ffffffff","curve":"stepped"},{"time":0.6667,"color":"ffffffff"},{"time":0.7667,"color":"ffffff00"}]},"WIN_Coin_b":{"color":[{"color":"ffffff00","curve":"stepped"},{"time":0.3333,"color":"ffffff00"},{"time":0.4333,"color":"ffffffc7"},{"time":0.6667,"color":"ffffffff","curve":"stepped"},{"time":0.8,"color":"ffffffff"},{"time":1.1,"color":"ffffff00"}]},"WIN_Coin_b2":{"color":[{"color":"ffffff00","curve":"stepped"},{"time":0.3333,"color":"ffffff00"},{"time":0.4333,"color":"ffffffc7"},{"time":0.6667,"color":"ffffffff","curve":"stepped"},{"time":0.8,"color":"ffffffff"},{"time":1.0667,"color":"ffffff00"}]},"WIN_Coin_b3":{"color":[{"color":"ffffff00","curve":"stepped"},{"time":0.3667,"color":"ffffff00"},{"time":0.4667,"color":"ffffffc7"},{"time":0.7,"color":"ffffffff","curve":"stepped"},{"time":0.8333,"color":"ffffffff"},{"time":0.9667,"color":"ffffff00"}]},"WIN_Coin_b4":{"color":[{"color":"ffffff00","curve":"stepped"},{"time":0.3667,"color":"ffffff00"},{"time":0.4667,"color":"ffffffc7"},{"time":0.7,"color":"ffffffff","curve":"stepped"},{"time":0.8333,"color":"ffffffff"},{"time":0.9667,"color":"ffffff00"}]},"WIN_Coin_c":{"color":[{"color":"ffffff00","curve":"stepped"},{"time":0.5,"color":"ffffff00"},{"time":0.6,"color":"ffffffc7"},{"time":0.7,"color":"ffffffff","curve":"stepped"},{"time":0.8,"color":"ffffffff"},{"time":0.9667,"color":"ffffff00"}]},"WIN_Coin_c2":{"color":[{"color":"ffffff00","curve":"stepped"},{"time":0.4667,"color":"ffffff00"},{"time":0.5667,"color":"ffffffc7"},{"time":0.6667,"color":"ffffffff","curve":"stepped"},{"time":0.7667,"color":"ffffffff"},{"time":0.9333,"color":"ffffff00"}]},"WIN_Coin_c3":{"color":[{"color":"ffffff00","curve":"stepped"},{"time":0.5,"color":"ffffff00"},{"time":0.6,"color":"ffffffc7"},{"time":0.6667,"color":"ffffffff","curve":"stepped"},{"time":0.8,"color":"ffffffff"},{"time":0.9333,"color":"ffffff00"}]},"WIN_Coin_c4":{"color":[{"color":"ffffff00","curve":"stepped"},{"time":0.5,"color":"ffffff00"},{"time":0.6,"color":"ffffffc7"},{"time":0.6667,"color":"ffffffff","curve":"stepped"},{"time":0.8,"color":"ffffffff"},{"time":1.0333,"color":"ffffff00"}]},"WIN_Coin_d":{"color":[{"color":"ffffff00"},{"time":0.3667,"color":"ffffff00"},{"time":0.4333,"color":"ffffffc7"},{"time":0.6,"color":"ffffffff","curve":"stepped"},{"time":0.7,"color":"ffffffff"},{"time":1,"color":"ffffff00"}]},"WIN_Coin_d2":{"color":[{"color":"ffffff00","curve":"stepped"},{"time":0.3667,"color":"ffffff00"},{"time":0.4333,"color":"ffffffc7"},{"time":0.6,"color":"ffffffff","curve":"stepped"},{"time":0.7,"color":"ffffffff"},{"time":1,"color":"ffffff00"}]},"WIN_Coin_d3":{"color":[{"color":"ffffff00"},{"time":0.4,"color":"ffffff00"},{"time":0.5,"color":"ffffffc7"},{"time":0.6667,"color":"ffffffff","curve":"stepped"},{"time":0.7667,"color":"ffffffff"},{"time":1.0333,"color":"ffffff00"}]},"WIN_Coin_d4":{"color":[{"color":"ffffff00","curve":"stepped"},{"time":0.3667,"color":"ffffff00"},{"time":0.4667,"color":"ffffffc7"},{"time":0.6333,"color":"ffffffff","curve":"stepped"},{"time":0.7333,"color":"ffffffff"},{"time":1,"color":"ffffff00"}]},"WIN_Coin_e":{"color":[{"color":"ffffff00","curve":"stepped"},{"time":0.4,"color":"ffffff00"},{"time":0.5,"color":"ffffffc7"},{"time":0.8,"color":"ffffffff","curve":"stepped"},{"time":0.9,"color":"ffffffff"},{"time":1.1667,"color":"ffffff00"}]},"WIN_Coin_e2":{"color":[{"color":"ffffff00","curve":"stepped"},{"time":0.3667,"color":"ffffff00"},{"time":0.4667,"color":"ffffffc7"},{"time":0.7667,"color":"ffffffff","curve":"stepped"},{"time":0.8667,"color":"ffffffff"},{"time":1.1333,"color":"ffffff00"}]},"WIN_Coin_e3":{"color":[{"color":"ffffff00","curve":"stepped"},{"time":0.3667,"color":"ffffff00"},{"time":0.4667,"color":"ffffffc7"},{"time":0.7667,"color":"ffffffff","curve":"stepped"},{"time":0.8667,"color":"ffffffff"},{"time":1.1333,"color":"ffffff00"}]},"WIN_Coin_e4":{"color":[{"color":"ffffff00","curve":"stepped"},{"time":0.3667,"color":"ffffff00"},{"time":0.4667,"color":"ffffffc7"},{"time":0.7667,"color":"ffffffff","curve":"stepped"},{"time":0.8667,"color":"ffffffff"},{"time":1.1333,"color":"ffffff00"}]},"WIN_Coin_e5":{"color":[{"color":"ffffff00","curve":"stepped"},{"time":0.3667,"color":"ffffff00"},{"time":0.5,"color":"ffffffc7"},{"time":0.7667,"color":"ffffffff","curve":"stepped"},{"time":0.9,"color":"ffffffff"},{"time":1.1333,"color":"ffffff00"}]},"WIN_Coin_e6":{"color":[{"color":"ffffff00","curve":"stepped"},{"time":0.3667,"color":"ffffff00"},{"time":0.5,"color":"ffffffc7"},{"time":0.7667,"color":"ffffffff","curve":"stepped"},{"time":0.9,"color":"ffffffff"},{"time":1.1333,"color":"ffffff00"}]},"WIN_Coin_e7":{"color":[{"color":"ffffff00","curve":"stepped"},{"time":0.3667,"color":"ffffff00"},{"time":0.5,"color":"ffffffc7"},{"time":0.7667,"color":"ffffffff","curve":"stepped"},{"time":0.9,"color":"ffffffff"},{"time":1.1333,"color":"ffffff00"}]},"WIN_Coin_e8":{"color":[{"color":"ffffff00","curve":"stepped"},{"time":0.4,"color":"ffffff00"},{"time":0.5333,"color":"ffffffc7"},{"time":0.8,"color":"ffffffff","curve":"stepped"},{"time":0.9333,"color":"ffffffff"},{"time":1.1667,"color":"ffffff00"}]},"WIN_Coin_e9":{"color":[{"color":"ffffff00","curve":"stepped"},{"time":0.3,"color":"ffffff00"},{"time":0.3667,"color":"ffffffc7"},{"time":0.6667,"color":"ffffffff","curve":"stepped"},{"time":0.8,"color":"ffffffff"},{"time":1.1,"color":"ffffff00"}]},"WIN_Coin_e10":{"color":[{"color":"ffffff00","curve":"stepped"},{"time":0.3667,"color":"ffffff00"},{"time":0.4333,"color":"ffffffc7"},{"time":0.7333,"color":"ffffffff","curve":"stepped"},{"time":0.8667,"color":"ffffffff"},{"time":1.1667,"color":"ffffff00"}]},"WIN_Coin_e11":{"color":[{"color":"ffffff00","curve":"stepped"},{"time":0.3,"color":"ffffff00"},{"time":0.3667,"color":"ffffffc7"},{"time":0.6667,"color":"ffffffff","curve":"stepped"},{"time":0.8,"color":"ffffffff"},{"time":1.1,"color":"ffffff00"}]},"WIN_Coin_e12":{"color":[{"color":"ffffff00","curve":"stepped"},{"time":0.3667,"color":"ffffff00"},{"time":0.4333,"color":"ffffffc7"},{"time":0.7333,"color":"ffffffff","curve":"stepped"},{"time":0.8667,"color":"ffffffff"},{"time":1.1667,"color":"ffffff00"}]},"WIN_Coin_e13":{"color":[{"color":"ffffff00","curve":"stepped"},{"time":0.3667,"color":"ffffff00"},{"time":0.4667,"color":"ffffffff","curve":"stepped"},{"time":0.8333,"color":"ffffffff"},{"time":1.1333,"color":"ffffff00"}]},"WIN_Coin_e14":{"color":[{"color":"ffffff00","curve":"stepped"},{"time":0.4333,"color":"ffffff00"},{"time":0.5333,"color":"ffffffff","curve":"stepped"},{"time":0.9,"color":"ffffffff"},{"time":1.2,"color":"ffffff00"}]},"WIN_Coin_e15":{"color":[{"color":"ffffff00","curve":"stepped"},{"time":0.3667,"color":"ffffff00"},{"time":0.4667,"color":"ffffffff","curve":"stepped"},{"time":0.8333,"color":"ffffffff"},{"time":1.1333,"color":"ffffff00"}]},"WIN_Coin_e16":{"color":[{"color":"ffffff00","curve":"stepped"},{"time":0.4333,"color":"ffffff00"},{"time":0.5333,"color":"ffffffff","curve":"stepped"},{"time":0.9,"color":"ffffffff"},{"time":1.2,"color":"ffffff00"}]}},"bones":{"FX_Light3":{"scale":[{"x":0,"y":0}]},"FX_Light5":{"scale":[{"x":0,"y":0}]},"FX_Light4":{"translate":[{"x":60.95,"y":11.88}],"scale":[{"x":0,"y":0}]},"FX_Light2":{"translate":[{"x":-100.38,"y":-16.8}],"scale":[{"x":0,"y":0}]},"FX_Light":{"translate":[{"x":22.61,"y":-101.75}],"scale":[{"x":0,"y":0}]},"FX_Light6":{"translate":[{"x":29.89,"y":62.22}],"scale":[{"x":0,"y":0}]},"FX_Light7":{"scale":[{"x":0,"y":0}]},"FX_Light8":{"scale":[{"x":0,"y":0}]},"FX_Light9":{"translate":[{"x":-38.46,"y":9.62}],"scale":[{"x":0,"y":0}]},"FX_Light10":{"translate":[{"x":23.44,"y":32.45}],"scale":[{"x":0,"y":0}]},"FX_Light11":{"translate":[{"x":-21.35,"y":-12.45}],"scale":[{"x":0,"y":0}]},"FX_Light12":{"rotate":[{"time":0.4,"angle":142.31}],"translate":[{"x":22.61,"y":-101.75}],"scale":[{"x":0,"y":0}]},"FX_Light13":{"rotate":[{"time":0.9333,"angle":142.31}],"translate":[{"x":-100.38,"y":-16.8}],"scale":[{"x":0,"y":0}]},"FX_Light14":{"rotate":[{"time":0.9333,"angle":142.31}],"scale":[{"x":0,"y":0},{"time":0.2,"x":0.6,"y":0.991},{"time":0.4333,"x":0.6,"y":0.6},{"time":0.9333,"x":0,"y":0}]},"FX_Light15":{"rotate":[{"time":1.2667,"angle":142.31}],"translate":[{"x":60.95,"y":11.88}],"scale":[{"x":0,"y":0,"curve":"stepped"},{"time":0.7667,"x":0,"y":0},{"time":1.0333,"x":0.3,"y":0.3,"curve":"stepped"},{"time":1.2333,"x":0.3,"y":0.3},{"time":1.4,"x":0,"y":0}]},"FX_Light16":{"rotate":[{"time":0.6},{"time":1.4,"angle":121.98}],"scale":[{"x":0,"y":0,"curve":"stepped"},{"time":0.6,"x":0,"y":0},{"time":0.8,"x":0.5,"y":0.5,"curve":"stepped"},{"time":1.0333,"x":0.5,"y":0.5},{"time":1.4,"x":0,"y":0}]},"FX_Light17":{"rotate":[{"time":0.9667,"angle":142.31}],"translate":[{"x":29.89,"y":62.22}],"scale":[{"x":0,"y":0},{"time":0.1667,"x":0.6,"y":0.6,"curve":"stepped"},{"time":0.4,"x":0.6,"y":0.6},{"time":0.9667,"x":0,"y":0}]},"FX_Light18":{"rotate":[{"time":0.6333,"angle":142.31}],"scale":[{"x":0,"y":0},{"time":0.1333,"x":0.46,"y":0.46},{"time":0.6333,"x":0,"y":0}]},"FX_Light19":{"rotate":[{"time":0.2667},{"time":1.2667,"angle":142.31}],"scale":[{"x":0,"y":0,"curve":"stepped"},{"time":0.2667,"x":0,"y":0},{"time":0.4667,"x":0.6,"y":0.6,"curve":"stepped"},{"time":0.7,"x":0.6,"y":0.6},{"time":1.2667,"x":0,"y":0}]},"FX_Light20":{"rotate":[{"time":0.9333,"angle":142.31}],"translate":[{"x":-38.46,"y":9.62}],"scale":[{"x":0,"y":0},{"time":0.2,"x":0.46,"y":0.46,"curve":"stepped"},{"time":0.4333,"x":0.46,"y":0.46},{"time":0.9333,"x":0,"y":0}]},"FX_Light21":{"rotate":[{"time":1.2667,"angle":142.31}],"translate":[{"x":23.44,"y":32.45}],"scale":[{"x":0,"y":0,"curve":"stepped"},{"time":0.3667,"x":0,"y":0},{"time":0.5667,"x":0.3,"y":0.3,"curve":"stepped"},{"time":0.8,"x":0.3,"y":0.3},{"time":1.1,"x":0,"y":0}]},"FX_Light22":{"rotate":[{"time":0.4,"angle":142.31}],"translate":[{"x":-21.35,"y":-12.45}],"scale":[{"x":0,"y":0}]},"Bowl_Center2":{"rotate":[{},{"time":0.2333,"angle":0.1},{"time":0.3667}],"translate":[{"time":0.0667},{"time":0.1333,"y":-0.47},{"time":0.2333,"y":-2.37},{"time":0.3667,"y":11.05},{"time":0.4333,"y":7.44},{"time":0.5667},{"time":0.6333,"y":0.79},{"time":0.7667}],"scale":[{},{"time":0.2333,"x":0.99,"y":0.99},{"time":0.4}]},"Bowl_Glow2":{"scale":[{"time":0.1667},{"time":0.5,"x":1.035,"y":1.053},{"time":1.1667}]},"Bowl_Ring_L":{"rotate":[{"time":0.0667},{"time":0.1333,"angle":-0.96},{"time":0.2333,"angle":-3.51},{"time":0.4,"angle":-0.96},{"time":0.5333,"angle":-4.73},{"time":0.6,"angle":-12.27},{"time":0.7667,"angle":4.65},{"time":0.9333,"angle":-2.43},{"time":1.1,"angle":1.51},{"time":1.2667}]},"Bowl_Ring_R":{"rotate":[{"time":0.0667},{"time":0.1333,"angle":0.66},{"time":0.2333,"angle":2.42},{"time":0.4,"angle":0.66},{"time":0.5333,"angle":4.97},{"time":0.6,"angle":13.2},{"time":0.7667,"angle":-4.13},{"time":0.9333,"angle":2.43},{"time":1.1,"angle":-1.37},{"time":1.2667}]},"WIN_Coin_a1_1":{"translate":[{"x":-91.8,"y":54.43,"curve":"stepped"},{"time":0.3333,"x":-91.8,"y":54.43},{"time":0.4,"x":-112.3,"y":69.8},{"time":0.5,"x":-132.79,"y":81.65},{"time":0.6333,"x":-163.53,"y":83.57},{"time":0.7667,"x":-199.4,"y":73.52},{"time":1,"x":-266.01,"y":26.78}]},"WIN_Coin_a1":{"rotate":[{"time":0.3333},{"time":0.7667,"angle":140.37}],"scale":[{"time":0.3333},{"time":0.5667,"x":1.3,"y":1.3}]},"WIN_Coin_b1_1":{"translate":[{"y":27.98,"curve":"stepped"},{"time":0.3333,"y":27.98},{"time":0.5667,"x":45.27,"y":58.68},{"time":0.8333,"x":97.91,"y":51.64},{"time":1.0667,"x":144.79,"y":8.61}]},"WIN_Coin_b1":{"rotate":[{"time":0.3333},{"time":0.9667,"angle":-140}],"scale":[{"time":0.3333},{"time":0.6667,"x":1.2,"y":1.2}]},"WIN_Coin_c1_1":{"translate":[{"x":-33.18,"y":41.27,"curve":"stepped"},{"time":0.5,"x":-33.18,"y":41.27},{"time":0.6667,"x":-55.51,"y":49.99},{"time":0.9,"x":-83.18,"y":33.14},{"time":1.0667,"x":-102.86,"y":-4.19}]},"WIN_Coin_c1":{"rotate":[{"time":0.5},{"time":0.9667,"angle":129.29}],"scale":[{"time":0.5},{"time":0.7,"x":1.3,"y":1.3}]},"WIN_Coin_d1_1":{"translate":[{"x":55.03,"y":92.26,"curve":"stepped"},{"time":0.3667,"x":55.03,"y":92.26},{"time":0.5,"x":80.47,"y":117.04},{"time":0.6667,"x":108.45,"y":122.2},{"time":0.8667,"x":141.51,"y":106.48},{"time":0.9667,"x":157.7,"y":87.6},{"time":1.1,"x":167.53,"y":59.08}]},"WIN_Coin_d1":{"rotate":[{"time":0.3667},{"time":1.0333,"angle":-98.62}],"scale":[{"time":0.3667},{"time":0.6,"x":1.2,"y":1.2}]},"WIN_Coin_e1_1":{"translate":[{"x":28.33,"y":118.16,"curve":"stepped"},{"time":0.4,"x":28.33,"y":118.16},{"time":0.5667,"x":48.59,"y":145.85},{"time":0.7333,"x":69.29,"y":153.89},{"time":0.9,"x":90.09,"y":157.01},{"time":1.0667,"x":111,"y":155.22},{"time":1.2333,"x":132.32,"y":134.58},{"time":1.4,"x":153.79,"y":107.39}],"scale":[{"x":0.8,"y":0.8}]},"WIN_Coin_e1":{"rotate":[{"time":0.4},{"time":1.3667,"angle":-164.35}],"scale":[{"time":0.4},{"time":0.8,"x":1.2,"y":1.2}]},"WIN_Coin_a2":{"rotate":[{"time":0.3667},{"time":0.8,"angle":140.37}],"scale":[{"time":0.3667},{"time":0.6,"x":1.3,"y":1.3}]},"WIN_Coin_a1_2":{"translate":[{"x":-91.8,"y":54.43,"curve":"stepped"},{"time":0.3667,"x":-91.8,"y":54.43},{"time":0.4333,"x":-112.3,"y":69.8},{"time":0.5333,"x":-132.79,"y":81.65},{"time":0.6667,"x":-163.53,"y":83.57},{"time":0.8,"x":-199.4,"y":73.52},{"time":1.0333,"x":-266.01,"y":26.78}]},"WIN_Coin_a1_1_bip2":{"translate":[{"x":11.92,"y":-2.52}],"shear":[{"x":-180}]},"WIN_Coin_e2":{"rotate":[{"time":0.3667},{"time":1.3333,"angle":-164.35}],"scale":[{"time":0.3667},{"time":0.7667,"x":1.2,"y":1.2}]},"WIN_Coin_e1_2":{"translate":[{"x":28.33,"y":118.16,"curve":"stepped"},{"time":0.3667,"x":28.33,"y":118.16},{"time":0.5333,"x":49.91,"y":147.49},{"time":0.7,"x":71.04,"y":155.53},{"time":0.8667,"x":92.05,"y":158.24},{"time":1.0333,"x":112.77,"y":147.85},{"time":1.2,"x":133.39,"y":132.53},{"time":1.3667,"x":153.79,"y":107.39}],"scale":[{"x":0.9,"y":0.9}]},"WIN_Coin_e1_1_bip2":{"translate":[{"x":81.18,"y":-17.82}],"shear":[{"x":-180}]},"WIN_Coin_b2":{"rotate":[{"time":0.3333},{"time":0.9667,"angle":-140}],"scale":[{"time":0.3333},{"time":0.6667,"x":1.2,"y":1.2}]},"WIN_Coin_b1_2":{"translate":[{"y":27.98,"curve":"stepped"},{"time":0.3333,"y":27.98},{"time":0.4333,"x":24.23,"y":49.25},{"time":0.5333,"x":43.61,"y":61.28},{"time":0.6667,"x":79.96,"y":68.91},{"time":0.8333,"x":107.63,"y":60.93},{"time":1.0333,"x":131.82,"y":27.28},{"time":1.2,"x":145.22,"y":-14.69}],"scale":[{"x":0.95,"y":0.95}]},"WIN_Coin_b1_1_bip2":{"translate":[{"x":25.98,"y":34.53}],"shear":[{"x":-180}]},"WIN_Coin_c2":{"rotate":[{"time":0.4667},{"time":0.9333,"angle":129.29}],"scale":[{"time":0.4667},{"time":0.6667,"x":1.3,"y":1.3}]},"WIN_Coin_c1_2":{"translate":[{"x":-33.18,"y":41.27,"curve":"stepped"},{"time":0.4667,"x":-33.18,"y":41.27},{"time":0.6,"x":-61.03,"y":44.87},{"time":0.7667,"x":-91.56,"y":22.64},{"time":0.9333,"x":-110.23,"y":-3.74}],"scale":[{"x":0.98,"y":0.98}]},"WIN_Coin_c1_1_bip2":{"translate":[{"x":-41.22,"y":101.75}],"shear":[{"x":-180}]},"WIN_Coin_d2":{"rotate":[{"time":0.3667},{"time":1.0333,"angle":-98.62}],"scale":[{"time":0.3667},{"time":0.6,"x":1.2,"y":1.2}]},"WIN_Coin_d1_2":{"translate":[{"x":55.03,"y":92.26,"curve":"stepped"},{"time":0.3667,"x":55.03,"y":92.26},{"time":0.5,"x":80.47,"y":117.04},{"time":0.6667,"x":108.45,"y":122.2},{"time":0.8667,"x":141.51,"y":106.48},{"time":0.9667,"x":157.7,"y":87.6},{"time":1.1,"x":167.53,"y":59.08}],"scale":[{"x":0.95,"y":0.95}]},"WIN_Coin_d1_1_bip2":{"rotate":[{"angle":-23.38}],"translate":[{"x":-15.6,"y":25.62}],"shear":[{"x":-180}]},"WIN_Coin_a3":{"rotate":[{"time":0.3333},{"time":0.7667,"angle":140.37}],"scale":[{"time":0.3333},{"time":0.5667,"x":1.3,"y":1.3}]},"WIN_Coin_a1_3":{"translate":[{"x":-91.8,"y":54.43,"curve":"stepped"},{"time":0.3333,"x":-91.8,"y":54.43},{"time":0.4,"x":-112.3,"y":69.8},{"time":0.5,"x":-132.79,"y":81.65},{"time":0.6333,"x":-163.53,"y":83.57},{"time":0.7667,"x":-199.4,"y":73.52},{"time":1,"x":-266.01,"y":26.78}],"scale":[{"x":0.95,"y":0.95}]},"WIN_Coin_a1_1_bip3":{"translate":[{"x":25.62,"y":75.75}]},"WIN_Coin_e3":{"rotate":[{"time":0.3667},{"time":1.3333,"angle":170.91}],"scale":[{"time":0.3667},{"time":0.7667,"x":1.2,"y":1.2}]},"WIN_Coin_e1_3":{"translate":[{"x":28.33,"y":118.16,"curve":"stepped"},{"time":0.3667,"x":28.33,"y":118.16},{"time":0.5333,"x":48.36,"y":156.5},{"time":0.7,"x":68.81,"y":176.01},{"time":0.8667,"x":89.61,"y":179.13},{"time":1.0333,"x":115.63,"y":168.43},{"time":1.2,"x":136.93,"y":148.62},{"time":1.3667,"x":153.79,"y":107.39}],"scale":[{"x":0.9,"y":0.9}]},"WIN_Coin_e1_1_bip3":{"translate":[{"x":46.79,"y":-25.62}]},"WIN_Coin_a4":{"rotate":[{"time":0.3333},{"time":0.7667,"angle":140.37}],"scale":[{"time":0.3333},{"time":0.5667,"x":1.3,"y":1.3}]},"WIN_Coin_a1_4":{"translate":[{"x":-91.8,"y":54.43,"curve":"stepped"},{"time":0.3333,"x":-91.8,"y":54.43},{"time":0.4,"x":-112.3,"y":69.8},{"time":0.5,"x":-132.79,"y":81.65},{"time":0.6333,"x":-163.53,"y":83.57},{"time":0.7667,"x":-199.4,"y":73.52},{"time":1,"x":-266.01,"y":26.78}]},"WIN_Coin_a1_1_bip4":{"translate":[{"x":16.87,"y":39.24}],"shear":[{"x":-180}]},"WIN_Coin_e4":{"rotate":[{"time":0.3667},{"time":1.3333,"angle":-164.35}],"scale":[{"time":0.3667},{"time":0.7667,"x":1.2,"y":1.2}]},"WIN_Coin_e1_4":{"translate":[{"x":28.33,"y":118.16,"curve":"stepped"},{"time":0.3667,"x":28.33,"y":118.16},{"time":0.5333,"x":50.09,"y":155.69},{"time":0.7,"x":71.36,"y":170.27},{"time":0.8667,"x":97.38,"y":177.38},{"time":1.0333,"x":117.99,"y":161.66},{"time":1.2,"x":136.83,"y":140.25},{"time":1.3667,"x":156.24,"y":107.34}]},"WIN_Coin_e1_1_bip4":{"translate":[{"x":33.42,"y":5.57}],"shear":[{"x":-180}]},"WIN_Coin_a5":{"rotate":[{"time":0.3667},{"time":0.8,"angle":140.37}],"scale":[{"time":0.3667},{"time":0.6,"x":1.3,"y":1.3}]},"WIN_Coin_a1_5":{"translate":[{"x":-91.8,"y":54.43,"curve":"stepped"},{"time":0.3667,"x":-91.8,"y":54.43},{"time":0.4667,"x":-112.3,"y":69.8},{"time":0.5333,"x":-132.79,"y":81.65},{"time":0.6333,"x":-163.53,"y":83.57},{"time":0.7667,"x":-199.4,"y":73.52},{"time":1,"x":-266.01,"y":26.78}]},"WIN_Coin_b3":{"rotate":[{"time":0.3667},{"time":0.9667,"angle":-140}],"scale":[{"time":0.3667},{"time":0.7,"x":1.2,"y":1.2}]},"WIN_Coin_b1_3":{"translate":[{"y":27.98,"curve":"stepped"},{"time":0.3667,"y":27.98},{"time":0.5667,"x":53.79,"y":66.06},{"time":0.7667,"x":99.1,"y":62.61},{"time":0.9667,"x":138.6,"y":30.75}],"scale":[{"x":0.8,"y":0.8}]},"WIN_Coin_c3":{"rotate":[{"time":0.5},{"time":0.9333,"angle":129.29}],"scale":[{"time":0.5},{"time":0.6667,"x":1.3,"y":1.3}]},"WIN_Coin_c1_3":{"translate":[{"x":-33.18,"y":41.27,"curve":"stepped"},{"time":0.5,"x":-33.18,"y":41.27},{"time":0.6333,"x":-65.65,"y":46.29},{"time":0.8,"x":-106.23,"y":38.4},{"time":1,"x":-138.69,"y":-4.05}]},"WIN_Coin_d3":{"rotate":[{"time":0.4},{"time":1.0667,"angle":-98.62}],"scale":[{"time":0.4},{"time":0.6667,"x":1.2,"y":1.2}]},"WIN_Coin_d1_3":{"translate":[{"x":55.03,"y":92.26,"curve":"stepped"},{"time":0.4,"x":55.03,"y":92.26},{"time":0.6667,"x":132.36,"y":84.98},{"time":0.9333,"x":181.16,"y":51.49},{"time":1.1667,"x":179.73,"y":-5.86}]},"WIN_Coin_e5":{"rotate":[{"time":0.3667},{"time":1.3333,"angle":-164.35}],"scale":[{"time":0.3667},{"time":0.7667,"x":1.2,"y":1.2}]},"WIN_Coin_e1_5":{"translate":[{"x":28.33,"y":118.16,"curve":"stepped"},{"time":0.3667,"x":28.33,"y":118.16},{"time":0.5333,"x":48.81,"y":153.94},{"time":0.7,"x":69.3,"y":168.38},{"time":0.8667,"x":89.79,"y":175.51},{"time":1.0667,"x":114.37,"y":163.19},{"time":1.2333,"x":134.86,"y":136.19},{"time":1.4,"x":155.34,"y":97.33}]},"WIN_Coin_a6":{"rotate":[{"time":0.3667},{"time":0.8,"angle":140.37}],"scale":[{"time":0.3667},{"time":0.6,"x":1.3,"y":1.3}]},"WIN_Coin_a1_6":{"translate":[{"x":-91.8,"y":54.43,"curve":"stepped"},{"time":0.3667,"x":-91.8,"y":54.43},{"time":0.4667,"x":-112.3,"y":69.8},{"time":0.5333,"x":-132.79,"y":81.65},{"time":0.6333,"x":-163.53,"y":83.57},{"time":0.7667,"x":-199.4,"y":73.52},{"time":1,"x":-266.01,"y":26.78}]},"WIN_Coin_a1_1_bip6":{"translate":[{"x":-61.27,"y":104.71}],"shear":[{"x":-180}]},"WIN_Coin_e6":{"rotate":[{"time":0.3667},{"time":1.3333,"angle":-164.35}],"scale":[{"time":0.3667},{"time":0.7667,"x":1.2,"y":1.2}]},"WIN_Coin_e1_6":{"translate":[{"x":28.33,"y":118.16,"curve":"stepped"},{"time":0.3667,"x":28.33,"y":118.16},{"time":0.5333,"x":55.25,"y":152.17},{"time":0.7,"x":78,"y":162.01},{"time":0.8667,"x":100.36,"y":169.49},{"time":1.0667,"x":123.44,"y":156.71},{"time":1.2333,"x":140.52,"y":133.61},{"time":1.4,"x":155.34,"y":97.33}],"scale":[{"x":0.9,"y":0.9}]},"WIN_Coin_e1_1_bip6":{"rotate":[{"angle":-9.77}],"translate":[{"x":57.93,"y":-5.57}],"shear":[{"x":-180}]},"WIN_Coin_b4":{"rotate":[{"time":0.3667},{"time":0.9667,"angle":-140}],"scale":[{"time":0.3667},{"time":0.7,"x":1.2,"y":1.2}]},"WIN_Coin_b1_4":{"translate":[{"y":27.98,"curve":"stepped"},{"time":0.3667,"y":27.98},{"time":0.5667,"x":43.94,"y":63.51},{"time":0.7667,"x":87.88,"y":63.9},{"time":0.9667,"x":135.17,"y":24.14}],"scale":[{"x":0.95,"y":0.95}]},"WIN_Coin_b1_1_bip4":{"translate":[{"x":-76.92,"y":18.94}],"shear":[{"x":-180}]},"WIN_Coin_c4":{"rotate":[{"time":0.5},{"time":0.9333,"angle":129.29}],"scale":[{"time":0.5},{"time":0.6667,"x":1.1,"y":1.1}]},"WIN_Coin_c1_4":{"translate":[{"x":-33.18,"y":41.27,"curve":"stepped"},{"time":0.5,"x":-33.18,"y":41.27},{"time":0.6667,"x":-59.08,"y":40.2},{"time":0.8667,"x":-90.16,"y":19.32},{"time":1.0333,"x":-116.05,"y":-37.12}],"scale":[{"x":0.98,"y":0.98}]},"WIN_Coin_c1_1_bip4":{"translate":[{"x":103.6,"y":35.65}],"shear":[{"x":-180}]},"WIN_Coin_d4":{"rotate":[{"time":0.3667},{"time":1.0333,"angle":-98.62}],"scale":[{"time":0.3667},{"time":0.6333,"x":1.2,"y":1.2}]},"WIN_Coin_d1_4":{"translate":[{"x":55.03,"y":92.26,"curve":"stepped"},{"time":0.3667,"x":55.03,"y":92.26},{"time":0.6,"x":104.55,"y":113.44},{"time":0.8667,"x":143.89,"y":97.76},{"time":1.1,"x":167.53,"y":59.08}],"scale":[{"x":0.95,"y":0.95}]},"WIN_Coin_d1_1_bip4":{"rotate":[{"angle":-23.38}],"translate":[{"x":14.48,"y":25.62}],"shear":[{"x":-180}]},"WIN_Coin_a7":{"rotate":[{"time":0.3667},{"time":0.8,"angle":140.37}],"scale":[{"time":0.3667},{"time":0.6,"x":1.3,"y":1.3}]},"WIN_Coin_a1_7":{"translate":[{"x":-91.8,"y":54.43,"curve":"stepped"},{"time":0.3667,"x":-91.8,"y":54.43},{"time":0.4667,"x":-112.3,"y":69.8},{"time":0.5333,"x":-132.79,"y":81.65},{"time":0.6333,"x":-163.53,"y":83.57},{"time":0.7667,"x":-199.4,"y":73.52},{"time":1,"x":-266.01,"y":26.78}],"scale":[{"x":0.95,"y":0.95}]},"WIN_Coin_a1_1_bip7":{"translate":[{"x":53.47,"y":98.03}]},"WIN_Coin_e7":{"rotate":[{"time":0.3667},{"time":1.3333,"angle":-111.77}],"scale":[{"time":0.3667},{"time":0.7667,"x":1.2,"y":1.2}]},"WIN_Coin_e1_7":{"translate":[{"x":28.33,"y":118.16,"curve":"stepped"},{"time":0.3667,"x":28.33,"y":118.16},{"time":0.5333,"x":48.81,"y":155.51},{"time":0.7,"x":69.3,"y":168.33},{"time":0.8667,"x":89.79,"y":177.99},{"time":1.0667,"x":114.37,"y":164.6},{"time":1.2333,"x":134.86,"y":148.81},{"time":1.4,"x":155.34,"y":97.33}],"scale":[{"x":0.9,"y":0.9}]},"WIN_Coin_e1_1_bip7":{"translate":[{"x":43.2,"y":-72.25}]},"WIN_Coin_a8":{"rotate":[{"time":0.4},{"time":0.8333,"angle":140.37}],"scale":[{"time":0.4},{"time":0.6333,"x":1.3,"y":1.3}]},"WIN_Coin_a1_8":{"translate":[{"x":-91.8,"y":54.43,"curve":"stepped"},{"time":0.4,"x":-91.8,"y":54.43},{"time":0.5,"x":-112.3,"y":69.8},{"time":0.5667,"x":-132.79,"y":81.65},{"time":0.6667,"x":-163.53,"y":83.57},{"time":0.8,"x":-199.4,"y":73.52},{"time":1.0333,"x":-266.01,"y":26.78}]},"WIN_Coin_a1_1_bip8":{"translate":[{"x":169.67,"y":6.09}]},"WIN_Coin_e8":{"rotate":[{"time":0.4},{"time":1.3667,"angle":-164.35}],"scale":[{"time":0.4},{"time":0.8,"x":1.2,"y":1.2}]},"WIN_Coin_e1_8":{"translate":[{"x":28.33,"y":118.16,"curve":"stepped"},{"time":0.4,"x":28.33,"y":118.16},{"time":0.5667,"x":31.9,"y":144.32},{"time":0.7333,"x":42.13,"y":158.87},{"time":0.9,"x":59.96,"y":160.14},{"time":1.1,"x":88.68,"y":148.89},{"time":1.2667,"x":118.68,"y":128.92},{"time":1.4333,"x":155.34,"y":97.33}]},"WIN_Coin_e1_1_bip8":{"rotate":[{"angle":29.81}],"translate":[{"x":116.18,"y":5.57}],"shear":[{"x":-180}]},"FG_Coin_new_bip2":{"translate":[{"y":51.24}],"scale":[{"x":0.95,"y":0.95}],"shear":[{"x":-180}]},"WIN_Coin_a1_1_bip5":{"translate":[{"y":51.24}]},"WIN_Coin_b1_1_bip3":{"rotate":[{"angle":11.55}],"translate":[{"x":-4.46,"y":24.51}]},"WIN_Coin_c1_1_bip3":{"translate":[{"x":-103.14,"y":-24.05}]},"WIN_Coin_d1_1_bip3":{"rotate":[{"angle":57.56}],"translate":[{"x":-7.8,"y":-10.03}]},"WIN_Coin_e1_1_bip5":{"translate":[{"x":35.65}],"scale":[{"x":0.8,"y":0.8}]},"WIN_Coin_a9":{"rotate":[{"time":0.2667},{"time":0.8333,"angle":140.37}],"scale":[{"time":0.2667},{"time":0.5,"x":1.3,"y":1.3}]},"WIN_Coin_a1_9":{"translate":[{"x":-91.8,"y":54.43,"curve":"stepped"},{"time":0.2667,"x":-91.8,"y":54.43},{"time":0.3667,"x":-112.3,"y":69.8},{"time":0.4333,"x":-132.79,"y":81.65},{"time":0.5667,"x":-163.53,"y":83.57},{"time":0.6667,"x":-199.4,"y":73.52},{"time":0.9333,"x":-266.01,"y":26.78}]},"WIN_Coin_e9":{"rotate":[{"time":0.3},{"time":1.2667,"angle":-164.35}],"scale":[{"time":0.3},{"time":0.6667,"x":1.2,"y":1.2}]},"WIN_Coin_e1_9":{"translate":[{"x":28.33,"y":118.16,"curve":"stepped"},{"time":0.3,"x":28.33,"y":118.16},{"time":0.4667,"x":48.17,"y":134.77},{"time":0.6333,"x":68.02,"y":140.79},{"time":0.8,"x":87.86,"y":142.83},{"time":1.0333,"x":115.65,"y":132.98},{"time":1.2,"x":135.5,"y":119.13},{"time":1.3667,"x":155.34,"y":97.33}]},"WIN_Coin_a10":{"rotate":[{"time":0.2667},{"time":0.7,"angle":140.37}],"scale":[{"time":0.2667},{"time":0.5,"x":1.3,"y":1.3}]},"WIN_Coin_a1_10":{"translate":[{"x":-91.8,"y":54.43,"curve":"stepped"},{"time":0.2667,"x":-91.8,"y":54.43},{"time":0.3667,"x":-112.3,"y":69.8},{"time":0.4333,"x":-132.79,"y":81.65},{"time":0.5667,"x":-163.53,"y":83.57},{"time":0.6667,"x":-199.4,"y":73.52},{"time":0.9333,"x":-266.01,"y":26.78}]},"WIN_Coin_a1_1_bip10":{"translate":[{"x":-30.08,"y":66.84}],"shear":[{"x":-180}]},"WIN_Coin_e10":{"rotate":[{"time":0.3667},{"time":1.3333,"angle":-164.35}],"scale":[{"time":0.3667},{"time":0.7333,"x":1.2,"y":1.2}]},"WIN_Coin_e1_10":{"translate":[{"x":28.33,"y":118.16,"curve":"stepped"},{"time":0.3667,"x":28.33,"y":118.16},{"time":0.5333,"x":48.17,"y":148.68},{"time":0.7,"x":68.02,"y":155.36},{"time":0.8667,"x":87.86,"y":158.95},{"time":1.1,"x":115.65,"y":144.9},{"time":1.2667,"x":135.5,"y":126.41},{"time":1.4333,"x":155.34,"y":97.33}],"scale":[{"x":0.9,"y":0.9}]},"WIN_Coin_e1_1_bip10":{"translate":[{"x":-41.22,"y":-17.82}],"shear":[{"x":-180}]},"WIN_Coin_a11":{"rotate":[{"time":0.3333},{"time":0.7667,"angle":140.37}],"scale":[{"time":0.3333},{"time":0.5667,"x":1.3,"y":1.3}]},"WIN_Coin_a1_11":{"translate":[{"x":-91.8,"y":54.43,"curve":"stepped"},{"time":0.3333,"x":-91.8,"y":54.43},{"time":0.4333,"x":-112.3,"y":69.8},{"time":0.5,"x":-132.79,"y":81.65},{"time":0.6333,"x":-163.53,"y":83.57},{"time":0.7333,"x":-199.4,"y":73.52},{"time":1,"x":-266.01,"y":26.78}],"scale":[{"x":0.95,"y":0.95}]},"WIN_Coin_a1_1_bip11":{"translate":[{"x":25.62,"y":75.75}]},"WIN_Coin_e11":{"rotate":[{"time":0.3},{"time":1.2667,"angle":-164.35}],"scale":[{"time":0.3},{"time":0.6667,"x":1.2,"y":1.2}]},"WIN_Coin_e1_11":{"translate":[{"x":28.33,"y":118.16,"curve":"stepped"},{"time":0.3,"x":28.33,"y":118.16},{"time":0.4667,"x":48.17,"y":150.67},{"time":0.6333,"x":68.02,"y":168.61},{"time":0.8,"x":87.86,"y":174.85},{"time":1.0333,"x":115.65,"y":166.09},{"time":1.2,"x":135.5,"y":136.35},{"time":1.3667,"x":155.34,"y":97.33}],"scale":[{"x":0.9,"y":0.9}]},"WIN_Coin_e1_1_bip11":{"translate":[{"x":46.79,"y":-22.8}]},"WIN_Coin_a12":{"rotate":[{"time":0.2667},{"time":0.7,"angle":140.37}],"scale":[{"time":0.2667},{"time":0.5,"x":1.3,"y":1.3}]},"WIN_Coin_a1_12":{"translate":[{"x":-91.8,"y":54.43,"curve":"stepped"},{"time":0.2667,"x":-91.8,"y":54.43},{"time":0.3667,"x":-112.3,"y":69.8},{"time":0.4333,"x":-132.79,"y":81.65},{"time":0.5667,"x":-163.53,"y":83.57},{"time":0.6667,"x":-199.4,"y":73.52},{"time":0.9333,"x":-266.01,"y":26.78}]},"WIN_Coin_a1_1_bip12":{"translate":[{"x":4.46,"y":66.84}],"shear":[{"x":-180}]},"WIN_Coin_e12":{"rotate":[{"time":0.3667},{"time":1.3333,"angle":-164.35}],"scale":[{"time":0.3667},{"time":0.7333,"x":1.2,"y":1.2}]},"WIN_Coin_e1_12":{"translate":[{"x":28.33,"y":118.16,"curve":"stepped"},{"time":0.3667,"x":28.33,"y":118.16},{"time":0.5333,"x":48.17,"y":150.01},{"time":0.7,"x":68.02,"y":165.96},{"time":0.8667,"x":87.86,"y":171.81},{"time":1.1,"x":115.65,"y":162},{"time":1.2667,"x":135.5,"y":132.98},{"time":1.4333,"x":155.34,"y":97.33}]},"WIN_Coin_e1_1_bip12":{"translate":[{"x":33.42,"y":5.57}],"shear":[{"x":-180}]},"FG_Coin_new_bip3":{"translate":[{"y":-47.4}],"scale":[{"x":0.8,"y":0.8}]},"WIN_Coin_a13":{"rotate":[{"time":0.3667},{"time":0.7667,"angle":140.37}],"scale":[{"time":0.3667},{"time":0.5667,"x":1.3,"y":1.3}]},"WIN_Coin_a1_13":{"translate":[{"x":-91.8,"y":54.43,"curve":"stepped"},{"time":0.3667,"x":-91.8,"y":54.43},{"time":0.4333,"x":-112.3,"y":69.8},{"time":0.5,"x":-132.79,"y":81.65},{"time":0.6333,"x":-163.53,"y":83.57},{"time":0.7667,"x":-199.4,"y":73.52},{"time":0.9667,"x":-266.01,"y":26.78}]},"WIN_Coin_e13":{"rotate":[{"time":0.3667},{"time":1.3,"angle":-118.4}],"scale":[{"time":0.3667},{"time":0.7667,"x":1.2,"y":1.2}]},"WIN_Coin_e1_13":{"translate":[{"x":28.33,"y":118.16,"curve":"stepped"},{"time":0.3667,"x":28.33,"y":118.16},{"time":0.5333,"x":50.75,"y":147.78},{"time":0.7,"x":72.17,"y":150.92},{"time":0.8667,"x":93.58,"y":153.74},{"time":1.0333,"x":114.43,"y":142},{"time":1.2,"x":135.19,"y":127.6},{"time":1.3667,"x":155.34,"y":97.33}]},"WIN_Coin_a14":{"rotate":[{"time":0.3667},{"time":0.7667,"angle":140.37}],"scale":[{"time":0.3667},{"time":0.5667,"x":1.3,"y":1.3}]},"WIN_Coin_a1_14":{"translate":[{"x":-91.8,"y":54.43,"curve":"stepped"},{"time":0.3667,"x":-91.8,"y":54.43},{"time":0.4333,"x":-112.3,"y":69.8},{"time":0.5,"x":-132.79,"y":81.65},{"time":0.6333,"x":-163.53,"y":83.57},{"time":0.7667,"x":-199.4,"y":73.52},{"time":0.9667,"x":-266.01,"y":26.78}]},"WIN_Coin_a1_1_bip14":{"translate":[{"x":-30.08,"y":66.84}],"shear":[{"x":-180}]},"WIN_Coin_e14":{"rotate":[{"time":0.4333},{"time":1.3667,"angle":-164.35}],"scale":[{"time":0.4333},{"time":0.8333,"x":1.2,"y":1.2}]},"WIN_Coin_e1_14":{"translate":[{"x":28.33,"y":118.16,"curve":"stepped"},{"time":0.4333,"x":28.33,"y":118.16},{"time":0.5333,"x":36.04,"y":137.19},{"time":0.6,"x":46.26,"y":154.85},{"time":0.7333,"x":63.28,"y":175.72},{"time":0.8333,"x":84.36,"y":188.47},{"time":0.9667,"x":106.74,"y":189.39},{"time":1.0667,"x":125.07,"y":171.4},{"time":1.2,"x":143.39,"y":142.63},{"time":1.3333,"x":152.23,"y":117.46},{"time":1.4333,"x":155.34,"y":97.33}],"scale":[{"x":0.9,"y":0.9}]},"WIN_Coin_e1_1_bip14":{"translate":[{"x":-31.34,"y":-31.82}],"shear":[{"x":-180}]},"WIN_Coin_a15":{"rotate":[{"time":0.4333},{"time":0.8333,"angle":140.37}],"scale":[{"time":0.4333},{"time":0.6333,"x":1.3,"y":1.3}]},"WIN_Coin_a1_15":{"translate":[{"x":-91.8,"y":54.43,"curve":"stepped"},{"time":0.4333,"x":-91.8,"y":54.43},{"time":0.5,"x":-112.3,"y":69.8},{"time":0.5667,"x":-132.79,"y":81.65},{"time":0.7,"x":-163.53,"y":83.57},{"time":0.8333,"x":-199.4,"y":73.52},{"time":1.0333,"x":-266.01,"y":26.78}],"scale":[{"x":0.95,"y":0.95}]},"WIN_Coin_a1_1_bip15":{"translate":[{"x":25.62,"y":75.75}]},"WIN_Coin_e15":{"rotate":[{"time":0.3667},{"time":1.3,"angle":-164.35}],"scale":[{"time":0.3667},{"time":0.7667,"x":1.2,"y":1.2}]},"WIN_Coin_e1_15":{"translate":[{"x":28.33,"y":118.16,"curve":"stepped"},{"time":0.3667,"x":28.33,"y":118.16},{"time":0.4667,"x":36.04,"y":137.19},{"time":0.5333,"x":46.26,"y":154.85},{"time":0.6667,"x":63.28,"y":175.72},{"time":0.7667,"x":84.36,"y":188.47},{"time":0.9,"x":106.74,"y":189.39},{"time":1,"x":125.07,"y":171.4},{"time":1.1333,"x":143.39,"y":142.63},{"time":1.2667,"x":152.23,"y":117.46},{"time":1.3667,"x":155.34,"y":97.33}],"scale":[{"x":0.9,"y":0.9}]},"WIN_Coin_e1_1_bip15":{"translate":[{"x":26.09,"y":9.19}]},"WIN_Coin_a16":{"rotate":[{"time":0.3667},{"time":0.7667,"angle":140.37}],"scale":[{"time":0.3667},{"time":0.5667,"x":1.3,"y":1.3}]},"WIN_Coin_a1_16":{"translate":[{"x":-91.8,"y":54.43,"curve":"stepped"},{"time":0.3667,"x":-91.8,"y":54.43},{"time":0.4333,"x":-112.3,"y":69.8},{"time":0.5,"x":-132.79,"y":81.65},{"time":0.6333,"x":-163.53,"y":83.57},{"time":0.7667,"x":-199.4,"y":73.52},{"time":0.9667,"x":-266.01,"y":26.78}]},"WIN_Coin_a1_1_bip16":{"translate":[{"x":4.46,"y":66.84}],"shear":[{"x":-180}]},"WIN_Coin_e16":{"rotate":[{"time":0.4333},{"time":1.3667,"angle":-164.35}],"scale":[{"time":0.4333},{"time":0.8333,"x":1.2,"y":1.2}]},"WIN_Coin_e1_16":{"translate":[{"x":28.33,"y":118.16,"curve":"stepped"},{"time":0.4333,"x":28.33,"y":118.16},{"time":0.5333,"x":36.04,"y":137.19},{"time":0.6,"x":46.26,"y":154.85},{"time":0.7333,"x":63.28,"y":175.72},{"time":0.8333,"x":84.36,"y":188.47},{"time":0.9667,"x":106.74,"y":189.39},{"time":1.0667,"x":125.07,"y":171.4},{"time":1.2,"x":143.39,"y":142.63},{"time":1.3333,"x":152.23,"y":117.46},{"time":1.4333,"x":155.34,"y":97.33}]},"WIN_Coin_e1_1_bip16":{"translate":[{"x":33.42,"y":5.57}],"shear":[{"x":-180}]},"FG_Coin_new_bip4":{"rotate":[{"angle":-2.17}],"translate":[{"x":26.19,"y":93.55}],"scale":[{"x":0.8,"y":0.8}],"shear":[{"x":-180}]},"FG_Money_Down_new":{"translate":[{},{"time":0.2333,"y":-2.77},{"time":0.4,"y":2.41},{"time":0.5667,"y":-0.92},{"time":0.6667}],"scale":[{"time":0.0667},{"time":0.2333,"y":0.99},{"time":0.4,"y":1.1},{"time":0.5667}]},"WIN_Coin_e1_1_bip9":{"translate":[{"x":-34.5,"y":-28.59}]},"WIN_Coin_e1_1_bip13":{"translate":[{"x":-54.07,"y":37.2}]},"WIN_Coin_a1_1_bip9":{"translate":[{"x":45.21,"y":25.43}]},"FG_Coin_new_bip":{"rotate":[{"angle":-1.25}]},"WIN_Coin_d1_1_bip1":{"translate":[{"x":-34.28,"y":-0.75}]},"FG_Money_Down_light3":{"scale":[{"time":0.2333},{"time":0.4,"y":1.044}]},"FG_Money_all_light_bip":{"scale":[{"time":0.2333},{"time":0.5667,"x":1.034,"y":1.034}]},"old":{"rotate":[{"time":1.5}]}}},"NG_Loop":{"slots":{"Bowl_Glow2":{"attachment":[{"name":null}]},"Bowl_In2":{"attachment":[{"name":null}]},"Bowl_Outer2":{"attachment":[{"name":null}]},"Bowl_Outer2_light":{"attachment":[{"name":null}]},"Bowl_Ring_L2":{"attachment":[{"name":null}]},"Bowl_Ring_L2_light":{"attachment":[{"name":null}]},"Bowl_Ring_L_light":{"color":[{"color":"ffffff00"},{"time":0.1667,"color":"ffffff82"},{"time":0.6667,"color":"ffffff00"}]},"Bowl_Ring_R2":{"attachment":[{"name":null}]},"Bowl_Ring_R2_light":{"attachment":[{"name":null}]},"Bowl_Ring_R3_light":{"color":[{"color":"ffffff00"},{"time":3.4,"color":"ffffff00"},{"time":3.6333,"color":"ffffff83"},{"time":4,"color":"ffffff00"}]},"Character/Character_Bowl/Character_Bowl_0005":{"color":[{"color":"ffffff00"},{"time":0.3,"color":"ffffffff"},{"time":0.6667,"color":"ffffff00"}]},"Character/Character_Bowl/Character_Bowl_0015":{"color":[{"color":"ffffff00","curve":"stepped"},{"time":0.1667,"color":"ffffff00"},{"time":0.5667,"color":"ffffffff"},{"time":1,"color":"ffffff00"}]},"Character/Character_Bowl/Character_Bowl_0025":{"color":[{"color":"ffffff00","curve":"stepped"},{"time":0.4,"color":"ffffff00"},{"time":0.8333,"color":"ffffffff"},{"time":1.3333,"color":"ffffff00"}]},"Character/Character_Bowl/Character_Bowl_0035":{"color":[{"color":"ffffff00","curve":"stepped"},{"time":0.7667,"color":"ffffff00"},{"time":1.1667,"color":"ffffffff"},{"time":1.7,"color":"ffffff00"}]},"Character/Character_Bowl/Character_Bowl_0045":{"color":[{"color":"ffffff00","curve":"stepped"},{"time":1.1,"color":"ffffff00"},{"time":1.5,"color":"ffffffff"},{"time":2,"color":"ffffff00"}]},"Character/Character_Bowl/Character_Bowl_0055":{"color":[{"color":"ffffff00","curve":"stepped"},{"time":1.3667,"color":"ffffff00"},{"time":1.8333,"color":"ffffffff"},{"time":2.3333,"color":"ffffff00"}]},"Character/Character_Bowl/Character_Bowl_0065":{"color":[{"color":"ffffff00","curve":"stepped"},{"time":1.6667,"color":"ffffff00"},{"time":2.1667,"color":"ffffffff"},{"time":2.7333,"color":"ffffff00"}]},"Character/Character_Bowl/Character_Bowl_0075":{"color":[{"color":"ffffff00","curve":"stepped"},{"time":1.9333,"color":"ffffff00"},{"time":2.5,"color":"ffffffff"},{"time":3.1,"color":"ffffff00"}]},"Character/Character_Bowl/Character_Bowl_0085":{"color":[{"color":"ffffff00","curve":"stepped"},{"time":2.2667,"color":"ffffff00"},{"time":2.8333,"color":"ffffffff"},{"time":3.3667,"color":"ffffff00"}]},"Character/Character_Bowl/Character_Bowl_0095":{"color":[{"color":"ffffff00","curve":"stepped"},{"time":2.6333,"color":"ffffff00"},{"time":3.1667,"color":"ffffffff"},{"time":3.6667,"color":"ffffff00"}]},"Character/Character_Bowl/Character_Bowl_0105":{"color":[{"color":"ffffff00","curve":"stepped"},{"time":2.9333,"color":"ffffff00"},{"time":3.5,"color":"ffffffff"},{"time":4,"color":"ffffff00"}]},"Character/Character_Bowl/Character_Bowl_0115":{"color":[{"color":"ffffff00","curve":"stepped"},{"time":3.2667,"color":"ffffff00"},{"time":3.7333,"color":"ffffffff"},{"time":4,"color":"ffffff00"}]},"Character/Character_Bowl/Character_Bowl_0118":{"color":[{"color":"ffffff00","curve":"stepped"},{"time":3.3333,"color":"ffffff00"},{"time":3.8333,"color":"ffffffff"},{"time":4,"color":"ffffff00"}]},"FG_Diamond_01":{"attachment":[{"name":null}]},"FG_Diamond_1":{"attachment":[{"name":null}]},"FG_Diamond_02":{"attachment":[{"name":null}]},"FG_Diamond_2":{"attachment":[{"name":null}]},"FG_Diamond_03":{"attachment":[{"name":null}]},"FG_Diamond_3":{"attachment":[{"name":null}]},"FG_Diamond_04":{"attachment":[{"name":null}]},"FG_Diamond_4":{"attachment":[{"name":null}]},"FG_Glow":{"attachment":[{"name":null}]},"FG_Glow_a":{"attachment":[{"name":null}]},"FG_Glow_b":{"attachment":[{"name":null}]},"FG_Money_Down":{"attachment":[{"name":null}]},"FG_Money_Down2":{"attachment":[{"name":null}]},"FG_Money_Down_light1":{"attachment":[{"name":null}]},"FG_Money_Down_light3":{"attachment":[{"name":null}]},"FG_Money_Down_light_up":{"attachment":[{"name":null}]},"FG_Money_Shadow":{"attachment":[{"name":null}]},"FG_Money_Shadow2":{"attachment":[{"name":null}]},"FG_Money_Up":{"attachment":[{"name":null}]},"FG_Money_Up2":{"attachment":[{"name":null}]},"Sym_WD/Sym_Words_Star2":{"color":[{"color":"ffffff00"}]},"Sym_WD/Sym_Words_Star8":{"color":[{"color":"ffffff00"}]},"Sym_WD/Sym_Words_Star9":{"color":[{"color":"ffffff00"}]},"Sym_WD/Sym_Words_Star10":{"color":[{"color":"ffffff00"}]},"Sym_WD/Sym_Words_Star11":{"color":[{"color":"ffffff00"}]},"Sym_WD/Sym_Words_Star12":{"attachment":[{"name":null}]},"Sym_WD/Sym_Words_Star13":{"color":[{"color":"ffffff00"}],"attachment":[{"name":null}]},"Sym_WD/Sym_Words_Star14":{"attachment":[{"name":null}]},"Sym_WD/Sym_Words_Star15":{"attachment":[{"name":null}]},"Sym_WD/Sym_Words_Star16":{"attachment":[{"name":null}]},"Sym_WD/Sym_Words_Star17":{"attachment":[{"name":null}]},"Sym_WD/Sym_Words_Star18":{"attachment":[{"name":null}]},"Sym_WD/Sym_Words_Star19":{"color":[{"color":"ffffff00"}],"attachment":[{"name":null}]},"Sym_WD/Sym_Words_Star20":{"color":[{"color":"ffffff00"}],"attachment":[{"name":null}]},"Sym_WD/Sym_Words_Star21":{"color":[{"color":"ffffff00"}],"attachment":[{"name":null}]},"Sym_WD/Sym_Words_Star22":{"color":[{"color":"ffffff00"}],"attachment":[{"name":null}]},"WIN_Coin_a1":{"attachment":[{"name":null}]},"WIN_Coin_a2":{"attachment":[{"name":null}]},"WIN_Coin_a3":{"attachment":[{"name":null}]},"WIN_Coin_a4":{"attachment":[{"name":null}]},"WIN_Coin_a5":{"attachment":[{"name":null}]},"WIN_Coin_a6":{"attachment":[{"name":null}]},"WIN_Coin_a7":{"attachment":[{"name":null}]},"WIN_Coin_a8":{"attachment":[{"name":null}]},"WIN_Coin_a9":{"attachment":[{"name":null}]},"WIN_Coin_a10":{"attachment":[{"name":null}]},"WIN_Coin_a11":{"attachment":[{"name":null}]},"WIN_Coin_a12":{"attachment":[{"name":null}]},"WIN_Coin_a13":{"attachment":[{"name":null}]},"WIN_Coin_a14":{"attachment":[{"name":null}]},"WIN_Coin_a15":{"attachment":[{"name":null}]},"WIN_Coin_a16":{"attachment":[{"name":null}]},"WIN_Coin_b":{"attachment":[{"name":null}]},"WIN_Coin_b2":{"attachment":[{"name":null}]},"WIN_Coin_b3":{"attachment":[{"name":null}]},"WIN_Coin_b4":{"attachment":[{"name":null}]},"WIN_Coin_c":{"attachment":[{"name":null}]},"WIN_Coin_c2":{"attachment":[{"name":null}]},"WIN_Coin_c3":{"attachment":[{"name":null}]},"WIN_Coin_c4":{"attachment":[{"name":null}]},"WIN_Coin_d":{"attachment":[{"name":null}]},"WIN_Coin_d2":{"attachment":[{"name":null}]},"WIN_Coin_d3":{"attachment":[{"name":null}]},"WIN_Coin_d4":{"attachment":[{"name":null}]},"WIN_Coin_e":{"attachment":[{"name":null}]},"WIN_Coin_e2":{"attachment":[{"name":null}]},"WIN_Coin_e3":{"attachment":[{"name":null}]},"WIN_Coin_e4":{"attachment":[{"name":null}]},"WIN_Coin_e5":{"attachment":[{"name":null}]},"WIN_Coin_e6":{"attachment":[{"name":null}]},"WIN_Coin_e7":{"attachment":[{"name":null}]},"WIN_Coin_e8":{"attachment":[{"name":null}]},"WIN_Coin_e9":{"attachment":[{"name":null}]},"WIN_Coin_e10":{"attachment":[{"name":null}]},"WIN_Coin_e11":{"attachment":[{"name":null}]},"WIN_Coin_e12":{"attachment":[{"name":null}]},"WIN_Coin_e13":{"attachment":[{"name":null}]},"WIN_Coin_e14":{"attachment":[{"name":null}]},"WIN_Coin_e15":{"attachment":[{"name":null}]},"WIN_Coin_e16":{"attachment":[{"name":null}]}},"bones":{"FX_Light":{"rotate":[{"time":0.1},{"time":1.9667,"angle":142.31}],"scale":[{"x":0,"y":0,"curve":"stepped"},{"time":0.1,"x":0,"y":0},{"time":0.5,"x":0.4,"y":0.4,"curve":"stepped"},{"time":0.9667,"x":0.4,"y":0.4},{"time":1.9667,"x":0,"y":0}]},"FX_Light2":{"rotate":[{"time":0.5667},{"time":2.4333,"angle":142.31}],"scale":[{"x":0,"y":0,"curve":"stepped"},{"time":0.5667,"x":0,"y":0},{"time":0.9667,"x":0.46,"y":0.46,"curve":"stepped"},{"time":1.4333,"x":0.46,"y":0.46},{"time":2.4333,"x":0,"y":0}]},"FX_Light3":{"rotate":[{"time":1.2},{"time":3.0667,"angle":142.31}],"scale":[{"x":0,"y":0,"curve":"stepped"},{"time":1.2,"x":0,"y":0},{"time":1.6,"x":0.6,"y":0.991},{"time":2.0667,"x":0.6,"y":0.6},{"time":3.0667,"x":0,"y":0}]},"FX_Light4":{"rotate":[{"time":0.8},{"time":3.7333,"angle":142.31}],"scale":[{"x":0,"y":0,"curve":"stepped"},{"time":1.9333,"x":0,"y":0},{"time":2.3333,"x":0.3,"y":0.3,"curve":"stepped"},{"time":2.8,"x":0.3,"y":0.3},{"time":3.3667,"x":0,"y":0}]},"FX_Light5":{"rotate":[{"time":2.4},{"time":4,"angle":121.98}],"scale":[{"x":0,"y":0,"curve":"stepped"},{"time":2.4,"x":0,"y":0},{"time":2.8,"x":0.5,"y":0.5,"curve":"stepped"},{"time":3.2667,"x":0.5,"y":0.5},{"time":4,"x":0,"y":0}]},"FX_Light6":{"rotate":[{"time":1.1},{"time":3.1333,"angle":142.31}],"scale":[{"x":0,"y":0,"curve":"stepped"},{"time":1.1,"x":0,"y":0},{"time":1.5,"x":0.6,"y":0.6,"curve":"stepped"},{"time":1.9667,"x":0.6,"y":0.6},{"time":3.1333,"x":0,"y":0}]},"FX_Light7":{"rotate":[{"time":0.5667},{"time":2.4333,"angle":142.31}],"scale":[{"x":0,"y":0,"curve":"stepped"},{"time":0.5667,"x":0,"y":0},{"time":0.9667,"x":0.46,"y":0.46,"curve":"stepped"},{"time":1.4333,"x":0.46,"y":0.46},{"time":2.4333,"x":0,"y":0}]},"FX_Light8":{"rotate":[{"time":1.1},{"time":3.1333,"angle":142.31}],"scale":[{"x":0,"y":0,"curve":"stepped"},{"time":1.1,"x":0,"y":0},{"time":1.5,"x":0.6,"y":0.6,"curve":"stepped"},{"time":1.9667,"x":0.6,"y":0.6},{"time":3.1333,"x":0,"y":0}]},"FX_Light9":{"rotate":[{"time":0.5667},{"time":2.4333,"angle":142.31}],"scale":[{"x":0,"y":0,"curve":"stepped"},{"time":0.5667,"x":0,"y":0},{"time":0.9667,"x":0.46,"y":0.46,"curve":"stepped"},{"time":1.4333,"x":0.46,"y":0.46},{"time":2.4333,"x":0,"y":0}]},"FX_Light10":{"rotate":[{"time":0.8},{"time":3.7333,"angle":142.31}],"scale":[{"x":0,"y":0,"curve":"stepped"},{"time":1.9333,"x":0,"y":0},{"time":2.3333,"x":0.3,"y":0.3,"curve":"stepped"},{"time":2.8,"x":0.3,"y":0.3},{"time":3.3667,"x":0,"y":0}]},"FX_Light11":{"rotate":[{"time":0.1},{"time":1.9667,"angle":142.31}],"scale":[{"x":0,"y":0,"curve":"stepped"},{"time":0.1,"x":0,"y":0},{"time":0.5,"x":0.4,"y":0.4,"curve":"stepped"},{"time":0.9667,"x":0.4,"y":0.4},{"time":1.9667,"x":0,"y":0}]},"FX_Light12":{"rotate":[{"time":0.1},{"time":1.9667,"angle":142.31}],"scale":[{"x":0,"y":0,"curve":"stepped"},{"time":0.1,"x":0,"y":0},{"time":0.5,"x":0.4,"y":0.4,"curve":"stepped"},{"time":0.9667,"x":0.4,"y":0.4},{"time":1.9667,"x":0,"y":0}]},"FX_Light13":{"rotate":[{"time":0.5667},{"time":2.4333,"angle":142.31}],"scale":[{"x":0,"y":0,"curve":"stepped"},{"time":0.5667,"x":0,"y":0},{"time":0.9667,"x":0.46,"y":0.46,"curve":"stepped"},{"time":1.4333,"x":0.46,"y":0.46},{"time":2.4333,"x":0,"y":0}]},"FX_Light14":{"rotate":[{"time":1.2},{"time":3.0667,"angle":142.31}],"scale":[{"x":0,"y":0,"curve":"stepped"},{"time":1.2,"x":0,"y":0},{"time":1.6,"x":0.6,"y":0.991},{"time":2.0667,"x":0.6,"y":0.6},{"time":3.0667,"x":0,"y":0}]},"FX_Light15":{"rotate":[{"time":0.8},{"time":3.7333,"angle":142.31}],"scale":[{"x":0,"y":0,"curve":"stepped"},{"time":1.9333,"x":0,"y":0},{"time":2.3333,"x":0.3,"y":0.3,"curve":"stepped"},{"time":2.8,"x":0.3,"y":0.3},{"time":3.3667,"x":0,"y":0}]},"FX_Light16":{"rotate":[{"time":2.4},{"time":4,"angle":121.98}],"scale":[{"x":0,"y":0,"curve":"stepped"},{"time":2.4,"x":0,"y":0},{"time":2.8,"x":0.5,"y":0.5,"curve":"stepped"},{"time":3.2667,"x":0.5,"y":0.5},{"time":4,"x":0,"y":0}]},"FX_Light17":{"rotate":[{"time":1.1},{"time":3.1333,"angle":142.31}],"scale":[{"x":0,"y":0,"curve":"stepped"},{"time":1.1,"x":0,"y":0},{"time":1.5,"x":0.6,"y":0.6,"curve":"stepped"},{"time":1.9667,"x":0.6,"y":0.6},{"time":3.1333,"x":0,"y":0}]},"FX_Light18":{"rotate":[{"time":0.5667},{"time":2.4333,"angle":142.31}],"scale":[{"x":0,"y":0,"curve":"stepped"},{"time":0.5667,"x":0,"y":0},{"time":0.9667,"x":0.46,"y":0.46,"curve":"stepped"},{"time":1.4333,"x":0.46,"y":0.46},{"time":2.4333,"x":0,"y":0}]},"FX_Light19":{"rotate":[{"time":1.1},{"time":3.1333,"angle":142.31}],"scale":[{"x":0,"y":0,"curve":"stepped"},{"time":1.1,"x":0,"y":0},{"time":1.5,"x":0.6,"y":0.6,"curve":"stepped"},{"time":1.9667,"x":0.6,"y":0.6},{"time":3.1333,"x":0,"y":0}]},"FX_Light20":{"rotate":[{"time":0.5667},{"time":2.4333,"angle":142.31}],"scale":[{"x":0,"y":0,"curve":"stepped"},{"time":0.5667,"x":0,"y":0},{"time":0.9667,"x":0.46,"y":0.46,"curve":"stepped"},{"time":1.4333,"x":0.46,"y":0.46},{"time":2.4333,"x":0,"y":0}]},"FX_Light21":{"rotate":[{"time":0.8},{"time":3.7333,"angle":142.31}],"scale":[{"x":0,"y":0,"curve":"stepped"},{"time":1.9333,"x":0,"y":0},{"time":2.3333,"x":0.3,"y":0.3,"curve":"stepped"},{"time":2.8,"x":0.3,"y":0.3},{"time":3.3667,"x":0,"y":0}]},"FX_Light22":{"rotate":[{"time":0.1},{"time":1.9667,"angle":142.31}],"scale":[{"x":0,"y":0,"curve":"stepped"},{"time":0.1,"x":0,"y":0},{"time":0.5,"x":0.4,"y":0.4,"curve":"stepped"},{"time":0.9667,"x":0.4,"y":0.4},{"time":1.9667,"x":0,"y":0}]}}}}}